{
"meta":{"test_sets":[],"test_metrics":[],"learn_metrics":[{"best_value":"Min","name":"RMSE"}],"launch_mode":"Train","parameters":"","iteration_count":1000,"learn_sets":["learn"],"name":"experiment"},
"iterations":[
{"learn":[196427.0987],"iteration":0,"passed_time":0.003186307488,"remaining_time":3.183121181},
{"learn":[190578.5255],"iteration":1,"passed_time":0.006228691062,"remaining_time":3.10811684},
{"learn":[185254.243],"iteration":2,"passed_time":0.009680529591,"remaining_time":3.217162667},
{"learn":[180550.1234],"iteration":3,"passed_time":0.01309751687,"remaining_time":3.261281701},
{"learn":[176134.3063],"iteration":4,"passed_time":0.01719248896,"remaining_time":3.421305304},
{"learn":[171680.7803],"iteration":5,"passed_time":0.02090659276,"remaining_time":3.463525533},
{"learn":[167753.9115],"iteration":6,"passed_time":0.02452207765,"remaining_time":3.478631872},
{"learn":[164171.0912],"iteration":7,"passed_time":0.02822305778,"remaining_time":3.499659164},
{"learn":[161142.0509],"iteration":8,"passed_time":0.03140249702,"remaining_time":3.457763839},
{"learn":[158225.1492],"iteration":9,"passed_time":0.03451283159,"remaining_time":3.416770327},
{"learn":[155535.0457],"iteration":10,"passed_time":0.03770087502,"remaining_time":3.3896514},
{"learn":[153016.3308],"iteration":11,"passed_time":0.04054438457,"remaining_time":3.33815433},
{"learn":[150673.1021],"iteration":12,"passed_time":0.04367306566,"remaining_time":3.315793523},
{"learn":[148565.8531],"iteration":13,"passed_time":0.04651753082,"remaining_time":3.276163242},
{"learn":[146412.3282],"iteration":14,"passed_time":0.04951944471,"remaining_time":3.251776869},
{"learn":[144569.4855],"iteration":15,"passed_time":0.05232633206,"remaining_time":3.218069421},
{"learn":[142906.3129],"iteration":16,"passed_time":0.05525712557,"remaining_time":3.195162026},
{"learn":[141142.9324],"iteration":17,"passed_time":0.05815414124,"remaining_time":3.172631483},
{"learn":[139499.465],"iteration":18,"passed_time":0.06118493042,"remaining_time":3.159074565},
{"learn":[138011.0913],"iteration":19,"passed_time":0.06400538702,"remaining_time":3.136263964},
{"learn":[136698.1028],"iteration":20,"passed_time":0.06682085105,"remaining_time":3.115124437},
{"learn":[135492.8569],"iteration":21,"passed_time":0.06994178522,"remaining_time":3.10923027},
{"learn":[134233.809],"iteration":22,"passed_time":0.07290281968,"remaining_time":3.096784992},
{"learn":[133047.995],"iteration":23,"passed_time":0.07586764994,"remaining_time":3.085284431},
{"learn":[131951.5387],"iteration":24,"passed_time":0.07897695555,"remaining_time":3.080101266},
{"learn":[131023.4565],"iteration":25,"passed_time":0.08191716775,"remaining_time":3.06874313},
{"learn":[130042.7303],"iteration":26,"passed_time":0.08540365391,"remaining_time":3.077694639},
{"learn":[129213.2988],"iteration":27,"passed_time":0.0883211818,"remaining_time":3.06600674},
{"learn":[128387.4212],"iteration":28,"passed_time":0.09098178813,"remaining_time":3.046321251},
{"learn":[127656.1502],"iteration":29,"passed_time":0.09390072473,"remaining_time":3.036123433},
{"learn":[126823.717],"iteration":30,"passed_time":0.09663598278,"remaining_time":3.020653784},
{"learn":[126062.527],"iteration":31,"passed_time":0.09999101003,"remaining_time":3.024728053},
{"learn":[125448.9065],"iteration":32,"passed_time":0.1027724401,"remaining_time":3.011543926},
{"learn":[124825.5733],"iteration":33,"passed_time":0.1055331821,"remaining_time":2.998383938},
{"learn":[124265.3273],"iteration":34,"passed_time":0.1083617048,"remaining_time":2.987687003},
{"learn":[123693.5159],"iteration":35,"passed_time":0.1112073442,"remaining_time":2.97788555},
{"learn":[123175.5131],"iteration":36,"passed_time":0.1143018382,"remaining_time":2.974937033},
{"learn":[122690.3349],"iteration":37,"passed_time":0.1170513448,"remaining_time":2.963247202},
{"learn":[122142.1689],"iteration":38,"passed_time":0.1198866624,"remaining_time":2.954130321},
{"learn":[121656.0076],"iteration":39,"passed_time":0.1226799721,"remaining_time":2.944319331},
{"learn":[121241.0668],"iteration":40,"passed_time":0.1257588754,"remaining_time":2.941530768},
{"learn":[120848.7515],"iteration":41,"passed_time":0.1286314755,"remaining_time":2.934022703},
{"learn":[120438.5178],"iteration":42,"passed_time":0.1317854394,"remaining_time":2.932992222},
{"learn":[120046.3629],"iteration":43,"passed_time":0.1344784652,"remaining_time":2.921850289},
{"learn":[119651.3911],"iteration":44,"passed_time":0.137195747,"remaining_time":2.911598631},
{"learn":[119281.347],"iteration":45,"passed_time":0.1400517435,"remaining_time":2.904551376},
{"learn":[118762.2193],"iteration":46,"passed_time":0.1429590624,"remaining_time":2.898723116},
{"learn":[118390.6171],"iteration":47,"passed_time":0.1461600628,"remaining_time":2.898841246},
{"learn":[118074.6665],"iteration":48,"passed_time":0.1490102345,"remaining_time":2.892014959},
{"learn":[117773.5272],"iteration":49,"passed_time":0.1518177507,"remaining_time":2.884537264},
{"learn":[117438.3556],"iteration":50,"passed_time":0.1545015625,"remaining_time":2.87494084},
{"learn":[117085.9905],"iteration":51,"passed_time":0.1576332158,"remaining_time":2.87377478},
{"learn":[116819.6932],"iteration":52,"passed_time":0.1603551023,"remaining_time":2.865212866},
{"learn":[116607.0641],"iteration":53,"passed_time":0.1632080356,"remaining_time":2.859162994},
{"learn":[116354.1228],"iteration":54,"passed_time":0.1660692861,"remaining_time":2.853372279},
{"learn":[116018.6597],"iteration":55,"passed_time":0.1688828505,"remaining_time":2.846882337},
{"learn":[115668.6756],"iteration":56,"passed_time":0.1717993208,"remaining_time":2.842223852},
{"learn":[115450.8079],"iteration":57,"passed_time":0.1750521906,"remaining_time":2.843089027},
{"learn":[115181.2296],"iteration":58,"passed_time":0.1786651339,"remaining_time":2.849557475},
{"learn":[114940.6394],"iteration":59,"passed_time":0.1820593702,"remaining_time":2.852263467},
{"learn":[114746.2862],"iteration":60,"passed_time":0.1852384122,"remaining_time":2.85145687},
{"learn":[114517.2453],"iteration":61,"passed_time":0.1883290771,"remaining_time":2.849236683},
{"learn":[114343.7065],"iteration":62,"passed_time":0.1920914703,"remaining_time":2.856979487},
{"learn":[114156.8534],"iteration":63,"passed_time":0.1953348889,"remaining_time":2.85677275},
{"learn":[113991.2281],"iteration":64,"passed_time":0.1982936815,"remaining_time":2.852378342},
{"learn":[113794.0402],"iteration":65,"passed_time":0.2012735978,"remaining_time":2.848326369},
{"learn":[113536.0453],"iteration":66,"passed_time":0.2047033173,"remaining_time":2.850570076},
{"learn":[113288.0518],"iteration":67,"passed_time":0.2082268591,"remaining_time":2.853932833},
{"learn":[113069.9546],"iteration":68,"passed_time":0.2116531628,"remaining_time":2.855783979},
{"learn":[112900.6848],"iteration":69,"passed_time":0.2148015908,"remaining_time":2.853792563},
{"learn":[112705.0101],"iteration":70,"passed_time":0.2180579905,"remaining_time":2.853181313},
{"learn":[112583.0589],"iteration":71,"passed_time":0.2221848392,"remaining_time":2.863715705},
{"learn":[112425.012],"iteration":72,"passed_time":0.2259011215,"remaining_time":2.868634789},
{"learn":[112302.6793],"iteration":73,"passed_time":0.2288978925,"remaining_time":2.864316871},
{"learn":[112179.4839],"iteration":74,"passed_time":0.231770591,"remaining_time":2.858503956},
{"learn":[112056.8326],"iteration":75,"passed_time":0.234749847,"remaining_time":2.854063929},
{"learn":[111845.9399],"iteration":76,"passed_time":0.238643554,"remaining_time":2.860623381},
{"learn":[111650.1587],"iteration":77,"passed_time":0.2419959283,"remaining_time":2.860515973},
{"learn":[111474.85],"iteration":78,"passed_time":0.245120575,"remaining_time":2.857671513},
{"learn":[111353.4527],"iteration":79,"passed_time":0.2482282066,"remaining_time":2.854624376},
{"learn":[111189.9575],"iteration":80,"passed_time":0.2512825393,"remaining_time":2.850971032},
{"learn":[111082.2254],"iteration":81,"passed_time":0.2546679005,"remaining_time":2.851038204},
{"learn":[110949.1676],"iteration":82,"passed_time":0.2577672077,"remaining_time":2.847861801},
{"learn":[110825.2151],"iteration":83,"passed_time":0.2607695872,"remaining_time":2.84363026},
{"learn":[110649.841],"iteration":84,"passed_time":0.2638719123,"remaining_time":2.840503527},
{"learn":[110537.3956],"iteration":85,"passed_time":0.2670922932,"remaining_time":2.838632046},
{"learn":[110442.8711],"iteration":86,"passed_time":0.2706391807,"remaining_time":2.840155999},
{"learn":[110266.9239],"iteration":87,"passed_time":0.2738979603,"remaining_time":2.838578861},
{"learn":[110164.2882],"iteration":88,"passed_time":0.2772424402,"remaining_time":2.837841157},
{"learn":[109977.7299],"iteration":89,"passed_time":0.2805405958,"remaining_time":2.836577135},
{"learn":[109889.1051],"iteration":90,"passed_time":0.2836602071,"remaining_time":2.833484926},
{"learn":[109792.5345],"iteration":91,"passed_time":0.2869352464,"remaining_time":2.831926128},
{"learn":[109627.3344],"iteration":92,"passed_time":0.2901852035,"remaining_time":2.830085802},
{"learn":[109513.3843],"iteration":93,"passed_time":0.2932554062,"remaining_time":2.826482957},
{"learn":[109433.8802],"iteration":94,"passed_time":0.2963628869,"remaining_time":2.823246449},
{"learn":[109295.6338],"iteration":95,"passed_time":0.2995116502,"remaining_time":2.820401373},
{"learn":[109165.0759],"iteration":96,"passed_time":0.3027776653,"remaining_time":2.818641565},
{"learn":[109057.3587],"iteration":97,"passed_time":0.3058784931,"remaining_time":2.81533062},
{"learn":[108858.5621],"iteration":98,"passed_time":0.3093461786,"remaining_time":2.815362696},
{"learn":[108741.8564],"iteration":99,"passed_time":0.3134787354,"remaining_time":2.821308619},
{"learn":[108666.3833],"iteration":100,"passed_time":0.3169558162,"remaining_time":2.821220582},
{"learn":[108576.7541],"iteration":101,"passed_time":0.3204618095,"remaining_time":2.821320637},
{"learn":[108465.0677],"iteration":102,"passed_time":0.3238780273,"remaining_time":2.82056884},
{"learn":[108349.8037],"iteration":103,"passed_time":0.3271433418,"remaining_time":2.818465714},
{"learn":[108268.3429],"iteration":104,"passed_time":0.3302908536,"remaining_time":2.815336324},
{"learn":[108184.7679],"iteration":105,"passed_time":0.3331392249,"remaining_time":2.809683651},
{"learn":[108127.8671],"iteration":106,"passed_time":0.3362363202,"remaining_time":2.806159196},
{"learn":[108014.0376],"iteration":107,"passed_time":0.3392883375,"remaining_time":2.802270343},
{"learn":[107933.9897],"iteration":108,"passed_time":0.3428454326,"remaining_time":2.802525509},
{"learn":[107851.9021],"iteration":109,"passed_time":0.3455684404,"remaining_time":2.795962836},
{"learn":[107785.986],"iteration":110,"passed_time":0.3482304618,"remaining_time":2.788980906},
{"learn":[107654.4427],"iteration":111,"passed_time":0.3511739673,"remaining_time":2.784307884},
{"learn":[107564.1596],"iteration":112,"passed_time":0.3540932217,"remaining_time":2.779475112},
{"learn":[107434.8588],"iteration":113,"passed_time":0.3571745954,"remaining_time":2.775935891},
{"learn":[107300.7383],"iteration":114,"passed_time":0.3601671531,"remaining_time":2.771721135},
{"learn":[107184.5845],"iteration":115,"passed_time":0.362768946,"remaining_time":2.764549554},
{"learn":[107103.2314],"iteration":116,"passed_time":0.3654359805,"remaining_time":2.757948469},
{"learn":[107016.6561],"iteration":117,"passed_time":0.3684339069,"remaining_time":2.753887338},
{"learn":[106911.5559],"iteration":118,"passed_time":0.3714784232,"remaining_time":2.750188998},
{"learn":[106844.9378],"iteration":119,"passed_time":0.3745223938,"remaining_time":2.746497554},
{"learn":[106737.7201],"iteration":120,"passed_time":0.377414543,"remaining_time":2.741713912},
{"learn":[106675.0153],"iteration":121,"passed_time":0.3802786459,"remaining_time":2.736759435},
{"learn":[106584.4909],"iteration":122,"passed_time":0.3835529149,"remaining_time":2.734763466},
{"learn":[106496.9451],"iteration":123,"passed_time":0.3862946456,"remaining_time":2.728984754},
{"learn":[106433.9951],"iteration":124,"passed_time":0.3897550661,"remaining_time":2.728285463},
{"learn":[106341.0339],"iteration":125,"passed_time":0.3924850594,"remaining_time":2.722475729},
{"learn":[106250.7532],"iteration":126,"passed_time":0.3951183327,"remaining_time":2.716049641},
{"learn":[106170.4645],"iteration":127,"passed_time":0.3977842716,"remaining_time":2.70990535},
{"learn":[106073.0062],"iteration":128,"passed_time":0.4008236542,"remaining_time":2.706336456},
{"learn":[105944.3152],"iteration":129,"passed_time":0.4039376301,"remaining_time":2.703274909},
{"learn":[105879.7062],"iteration":130,"passed_time":0.4065509171,"remaining_time":2.696891198},
{"learn":[105809.0228],"iteration":131,"passed_time":0.4093048047,"remaining_time":2.691489171},
{"learn":[105732.1627],"iteration":132,"passed_time":0.4118565809,"remaining_time":2.684809441},
{"learn":[105663.7949],"iteration":133,"passed_time":0.4146587385,"remaining_time":2.679809459},
{"learn":[105550.7651],"iteration":134,"passed_time":0.417556942,"remaining_time":2.675457443},
{"learn":[105469.3501],"iteration":135,"passed_time":0.4209649367,"remaining_time":2.674365481},
{"learn":[105298.7671],"iteration":136,"passed_time":0.4239096206,"remaining_time":2.670321187},
{"learn":[105178.2614],"iteration":137,"passed_time":0.4266015319,"remaining_time":2.664713916},
{"learn":[105106.7898],"iteration":138,"passed_time":0.4293530574,"remaining_time":2.659517859},
{"learn":[104986.182],"iteration":139,"passed_time":0.43249177,"remaining_time":2.656735159},
{"learn":[104927.2929],"iteration":140,"passed_time":0.4356832859,"remaining_time":2.654269096},
{"learn":[104775.7111],"iteration":141,"passed_time":0.4387429248,"remaining_time":2.650995982},
{"learn":[104676.1979],"iteration":142,"passed_time":0.441496733,"remaining_time":2.645893008},
{"learn":[104585.9813],"iteration":143,"passed_time":0.4442074722,"remaining_time":2.64056664},
{"learn":[104546.4828],"iteration":144,"passed_time":0.4469610817,"remaining_time":2.635529137},
{"learn":[104480.3847],"iteration":145,"passed_time":0.4500358597,"remaining_time":2.632401536},
{"learn":[104417.2795],"iteration":146,"passed_time":0.4529264866,"remaining_time":2.628206075},
{"learn":[104336.9868],"iteration":147,"passed_time":0.4556620125,"remaining_time":2.623135369},
{"learn":[104268.5812],"iteration":148,"passed_time":0.4584684765,"remaining_time":2.618501164},
{"learn":[104197.4199],"iteration":149,"passed_time":0.4611952612,"remaining_time":2.613439813},
{"learn":[104148.1361],"iteration":150,"passed_time":0.4641219961,"remaining_time":2.609533607},
{"learn":[103996.8561],"iteration":151,"passed_time":0.4676435315,"remaining_time":2.60895865},
{"learn":[103956.0246],"iteration":152,"passed_time":0.4706929728,"remaining_time":2.605731686},
{"learn":[103902.0401],"iteration":153,"passed_time":0.4735100458,"remaining_time":2.601230512},
{"learn":[103811.8334],"iteration":154,"passed_time":0.4763457218,"remaining_time":2.596852483},
{"learn":[103709.223],"iteration":155,"passed_time":0.4794711174,"remaining_time":2.594061686},
{"learn":[103555.6597],"iteration":156,"passed_time":0.4825711051,"remaining_time":2.591130201},
{"learn":[103475.9798],"iteration":157,"passed_time":0.4854340813,"remaining_time":2.586933522},
{"learn":[103423.4176],"iteration":158,"passed_time":0.488189629,"remaining_time":2.582185396},
{"learn":[103373.3615],"iteration":159,"passed_time":0.4908549051,"remaining_time":2.576988252},
{"learn":[103304.5475],"iteration":160,"passed_time":0.4935191067,"remaining_time":2.57181696},
{"learn":[103231.1252],"iteration":161,"passed_time":0.4968245511,"remaining_time":2.569993666},
{"learn":[103170.6288],"iteration":162,"passed_time":0.4998119085,"remaining_time":2.566518818},
{"learn":[103087.4704],"iteration":163,"passed_time":0.5036500601,"remaining_time":2.567386892},
{"learn":[103006.9525],"iteration":164,"passed_time":0.5065468358,"remaining_time":2.563433987},
{"learn":[102928.078],"iteration":165,"passed_time":0.509230282,"remaining_time":2.558422019},
{"learn":[102833.229],"iteration":166,"passed_time":0.5130165129,"remaining_time":2.558938654},
{"learn":[102743.202],"iteration":167,"passed_time":0.5161251579,"remaining_time":2.556048401},
{"learn":[102670.0841],"iteration":168,"passed_time":0.5194091581,"remaining_time":2.554017813},
{"learn":[102608.0453],"iteration":169,"passed_time":0.5225936633,"remaining_time":2.551486709},
{"learn":[102545.2858],"iteration":170,"passed_time":0.5254994867,"remaining_time":2.547596927},
{"learn":[102431.5449],"iteration":171,"passed_time":0.5293333159,"remaining_time":2.548185962},
{"learn":[102370.08],"iteration":172,"passed_time":0.5325863973,"remaining_time":2.545947691},
{"learn":[102310.9204],"iteration":173,"passed_time":0.5362006077,"remaining_time":2.54541208},
{"learn":[102259.8318],"iteration":174,"passed_time":0.5390805033,"remaining_time":2.541379516},
{"learn":[102161.1438],"iteration":175,"passed_time":0.5426550299,"remaining_time":2.540612185},
{"learn":[102079.0625],"iteration":176,"passed_time":0.5464074746,"remaining_time":2.540640404},
{"learn":[101977.1073],"iteration":177,"passed_time":0.5501662359,"remaining_time":2.540655314},
{"learn":[101914.1871],"iteration":178,"passed_time":0.5531683436,"remaining_time":2.537157599},
{"learn":[101838.8121],"iteration":179,"passed_time":0.5562333538,"remaining_time":2.533951945},
{"learn":[101762.7192],"iteration":180,"passed_time":0.5592626873,"remaining_time":2.530586414},
{"learn":[101696.9272],"iteration":181,"passed_time":0.5625871938,"remaining_time":2.528551234},
{"learn":[101628.0981],"iteration":182,"passed_time":0.5655074261,"remaining_time":2.524697088},
{"learn":[101528.9622],"iteration":183,"passed_time":0.5685865291,"remaining_time":2.521557651},
{"learn":[101475.9239],"iteration":184,"passed_time":0.5722986414,"remaining_time":2.521207528},
{"learn":[101424.1295],"iteration":185,"passed_time":0.5751582276,"remaining_time":2.517090308},
{"learn":[101367.1839],"iteration":186,"passed_time":0.5783545218,"remaining_time":2.514450408},
{"learn":[101294.5125],"iteration":187,"passed_time":0.5813609438,"remaining_time":2.510984502},
{"learn":[101238.3968],"iteration":188,"passed_time":0.5841472136,"remaining_time":2.506578784},
{"learn":[101145.8167],"iteration":189,"passed_time":0.5874734589,"remaining_time":2.504492114},
{"learn":[101075.3363],"iteration":190,"passed_time":0.5904075405,"remaining_time":2.500731415},
{"learn":[101017.9005],"iteration":191,"passed_time":0.5937479434,"remaining_time":2.498689262},
{"learn":[100960.3259],"iteration":192,"passed_time":0.5966345445,"remaining_time":2.494736152},
{"learn":[100899.0225],"iteration":193,"passed_time":0.5994243323,"remaining_time":2.490391814},
{"learn":[100815.8424],"iteration":194,"passed_time":0.6025976842,"remaining_time":2.48764685},
{"learn":[100739.0107],"iteration":195,"passed_time":0.6054747427,"remaining_time":2.483682108},
{"learn":[100673.487],"iteration":196,"passed_time":0.6083570824,"remaining_time":2.479749935},
{"learn":[100609.4546],"iteration":197,"passed_time":0.6112097867,"remaining_time":2.475708328},
{"learn":[100559.325],"iteration":198,"passed_time":0.6143800842,"remaining_time":2.472957022},
{"learn":[100475.3169],"iteration":199,"passed_time":0.6176639605,"remaining_time":2.470655842},
{"learn":[100402.831],"iteration":200,"passed_time":0.6208317512,"remaining_time":2.467883429},
{"learn":[100337.7149],"iteration":201,"passed_time":0.6242544917,"remaining_time":2.466114279},
{"learn":[100230.3334],"iteration":202,"passed_time":0.6273283685,"remaining_time":2.462959161},
{"learn":[100170.1878],"iteration":203,"passed_time":0.6302715706,"remaining_time":2.459294952},
{"learn":[100114.0462],"iteration":204,"passed_time":0.6334979097,"remaining_time":2.456735796},
{"learn":[100050.4924],"iteration":205,"passed_time":0.6362637437,"remaining_time":2.452395206},
{"learn":[100000.0619],"iteration":206,"passed_time":0.6389276886,"remaining_time":2.447679503},
{"learn":[99931.50999],"iteration":207,"passed_time":0.6419424672,"remaining_time":2.444319395},
{"learn":[99887.50816],"iteration":208,"passed_time":0.6448488641,"remaining_time":2.4405524},
{"learn":[99824.0844],"iteration":209,"passed_time":0.6480583943,"remaining_time":2.437933959},
{"learn":[99767.56759],"iteration":210,"passed_time":0.6507916616,"remaining_time":2.43352901},
{"learn":[99695.61779],"iteration":211,"passed_time":0.6535238878,"remaining_time":2.42913596},
{"learn":[99650.27696],"iteration":212,"passed_time":0.6564311967,"remaining_time":2.425405407},
{"learn":[99601.3528],"iteration":213,"passed_time":0.6592972022,"remaining_time":2.421530845},
{"learn":[99564.19345],"iteration":214,"passed_time":0.6626179535,"remaining_time":2.419326016},
{"learn":[99476.16762],"iteration":215,"passed_time":0.6661668453,"remaining_time":2.41793892},
{"learn":[99413.50646],"iteration":216,"passed_time":0.6689823327,"remaining_time":2.41388556},
{"learn":[99364.61888],"iteration":217,"passed_time":0.6718739663,"remaining_time":2.410116705},
{"learn":[99302.54584],"iteration":218,"passed_time":0.6749461766,"remaining_time":2.406999835},
{"learn":[99229.1694],"iteration":219,"passed_time":0.6781501442,"remaining_time":2.404350511},
{"learn":[99173.23841],"iteration":220,"passed_time":0.6811683775,"remaining_time":2.401041475},
{"learn":[99122.04002],"iteration":221,"passed_time":0.6838430931,"remaining_time":2.3965312},
{"learn":[99055.93593],"iteration":222,"passed_time":0.6865183027,"remaining_time":2.392039108},
{"learn":[99004.27805],"iteration":223,"passed_time":0.6897351861,"remaining_time":2.389439752},
{"learn":[98946.51549],"iteration":224,"passed_time":0.6927010695,"remaining_time":2.38597035},
{"learn":[98915.59736],"iteration":225,"passed_time":0.6956689814,"remaining_time":2.382512352},
{"learn":[98877.22352],"iteration":226,"passed_time":0.6983707905,"remaining_time":2.378152516},
{"learn":[98835.5008],"iteration":227,"passed_time":0.7011715977,"remaining_time":2.374142427},
{"learn":[98778.29091],"iteration":228,"passed_time":0.704050561,"remaining_time":2.370406037},
{"learn":[98721.09589],"iteration":229,"passed_time":0.7070368239,"remaining_time":2.367036323},
{"learn":[98657.88264],"iteration":230,"passed_time":0.7101474043,"remaining_time":2.364083783},
{"learn":[98582.73846],"iteration":231,"passed_time":0.7128765452,"remaining_time":2.359867184},
{"learn":[98536.6251],"iteration":232,"passed_time":0.7157036123,"remaining_time":2.355985711},
{"learn":[98485.83168],"iteration":233,"passed_time":0.7185593979,"remaining_time":2.35220726},
{"learn":[98432.27766],"iteration":234,"passed_time":0.7219953659,"remaining_time":2.35032534},
{"learn":[98384.36373],"iteration":235,"passed_time":0.7251116951,"remaining_time":2.347395487},
{"learn":[98324.6803],"iteration":236,"passed_time":0.7280414791,"remaining_time":2.343863496},
{"learn":[98261.52155],"iteration":237,"passed_time":0.7308431939,"remaining_time":2.339926528},
{"learn":[98200.71971],"iteration":238,"passed_time":0.7335653466,"remaining_time":2.335745727},
{"learn":[98158.26257],"iteration":239,"passed_time":0.7364059826,"remaining_time":2.331952278},
{"learn":[98108.48706],"iteration":240,"passed_time":0.7396891733,"remaining_time":2.329560508},
{"learn":[98047.64465],"iteration":241,"passed_time":0.7427808477,"remaining_time":2.326561498},
{"learn":[97951.08813],"iteration":242,"passed_time":0.7459372643,"remaining_time":2.323763412},
{"learn":[97917.37747],"iteration":243,"passed_time":0.7486621466,"remaining_time":2.31962534},
{"learn":[97877.20067],"iteration":244,"passed_time":0.751396528,"remaining_time":2.315528076},
{"learn":[97832.74757],"iteration":245,"passed_time":0.7545421232,"remaining_time":2.31270228},
{"learn":[97785.69573],"iteration":246,"passed_time":0.7577567621,"remaining_time":2.31008438},
{"learn":[97702.63035],"iteration":247,"passed_time":0.7609698725,"remaining_time":2.307457033},
{"learn":[97654.77281],"iteration":248,"passed_time":0.7642089511,"remaining_time":2.304903302},
{"learn":[97613.24865],"iteration":249,"passed_time":0.7672665129,"remaining_time":2.301799539},
{"learn":[97577.17802],"iteration":250,"passed_time":0.7714169299,"remaining_time":2.301957293},
{"learn":[97540.80636],"iteration":251,"passed_time":0.7749489624,"remaining_time":2.300245333},
{"learn":[97499.63248],"iteration":252,"passed_time":0.7782789419,"remaining_time":2.297922409},
{"learn":[97417.51827],"iteration":253,"passed_time":0.7817652758,"remaining_time":2.296050771},
{"learn":[97386.66661],"iteration":254,"passed_time":0.7857578907,"remaining_time":2.295645602},
{"learn":[97346.89863],"iteration":255,"passed_time":0.7891532301,"remaining_time":2.293476575},
{"learn":[97306.89586],"iteration":256,"passed_time":0.7925754791,"remaining_time":2.291375802},
{"learn":[97262.00577],"iteration":257,"passed_time":0.7958846194,"remaining_time":2.288939487},
{"learn":[97220.31463],"iteration":258,"passed_time":0.7990436664,"remaining_time":2.286067015},
{"learn":[97193.48094],"iteration":259,"passed_time":0.8021519642,"remaining_time":2.283047898},
{"learn":[97139.06892],"iteration":260,"passed_time":0.8055754372,"remaining_time":2.280920491},
{"learn":[97097.53369],"iteration":261,"passed_time":0.8087732593,"remaining_time":2.278147578},
{"learn":[97057.55491],"iteration":262,"passed_time":0.8120172121,"remaining_time":2.275500705},
{"learn":[97002.99519],"iteration":263,"passed_time":0.8158402788,"remaining_time":2.274463808},
{"learn":[96967.5065],"iteration":264,"passed_time":0.8191172858,"remaining_time":2.27189134},
{"learn":[96931.44467],"iteration":265,"passed_time":0.8224111636,"remaining_time":2.269360128},
{"learn":[96898.5397],"iteration":266,"passed_time":0.8256465717,"remaining_time":2.266662686},
{"learn":[96844.02522],"iteration":267,"passed_time":0.8288670484,"remaining_time":2.263920446},
{"learn":[96791.90453],"iteration":268,"passed_time":0.8319856538,"remaining_time":2.260897818},
{"learn":[96750.46302],"iteration":269,"passed_time":0.8353625906,"remaining_time":2.25857293},
{"learn":[96710.73341],"iteration":270,"passed_time":0.8383265511,"remaining_time":2.255129357},
{"learn":[96653.05371],"iteration":271,"passed_time":0.8417346625,"remaining_time":2.252878067},
{"learn":[96621.52794],"iteration":272,"passed_time":0.8451081916,"remaining_time":2.25052621},
{"learn":[96562.78706],"iteration":273,"passed_time":0.8482202315,"remaining_time":2.247474044},
{"learn":[96522.19823],"iteration":274,"passed_time":0.8516622327,"remaining_time":2.245291341},
{"learn":[96481.26807],"iteration":275,"passed_time":0.8551664228,"remaining_time":2.243262645},
{"learn":[96428.20206],"iteration":276,"passed_time":0.8585348504,"remaining_time":2.240868942},
{"learn":[96397.59469],"iteration":277,"passed_time":0.8614946726,"remaining_time":2.237407027},
{"learn":[96360.95267],"iteration":278,"passed_time":0.8645434424,"remaining_time":2.234178573},
{"learn":[96311.70583],"iteration":279,"passed_time":0.8680955869,"remaining_time":2.232245795},
{"learn":[96275.00742],"iteration":280,"passed_time":0.8712919709,"remaining_time":2.2293912},
{"learn":[96237.86547],"iteration":281,"passed_time":0.8742138691,"remaining_time":2.225835312},
{"learn":[96211.47413],"iteration":282,"passed_time":0.8772687485,"remaining_time":2.222620822},
{"learn":[96159.9245],"iteration":283,"passed_time":0.8800271837,"remaining_time":2.218660083},
{"learn":[96118.08819],"iteration":284,"passed_time":0.8829375717,"remaining_time":2.215088996},
{"learn":[96091.05808],"iteration":285,"passed_time":0.8856863334,"remaining_time":2.211119028},
{"learn":[96055.96305],"iteration":286,"passed_time":0.888492649,"remaining_time":2.207300553},
{"learn":[96018.62302],"iteration":287,"passed_time":0.8921692014,"remaining_time":2.205640526},
{"learn":[95974.66728],"iteration":288,"passed_time":0.8951307353,"remaining_time":2.202207449},
{"learn":[95914.76139],"iteration":289,"passed_time":0.8980253475,"remaining_time":2.198613782},
{"learn":[95875.50062],"iteration":290,"passed_time":0.9009204061,"remaining_time":2.195026007},
{"learn":[95828.41847],"iteration":291,"passed_time":0.9038407931,"remaining_time":2.191504389},
{"learn":[95785.1624],"iteration":292,"passed_time":0.9075307947,"remaining_time":2.189843931},
{"learn":[95736.68758],"iteration":293,"passed_time":0.9103436997,"remaining_time":2.186063442},
{"learn":[95713.37479],"iteration":294,"passed_time":0.9130301611,"remaining_time":2.181987334},
{"learn":[95667.7746],"iteration":295,"passed_time":0.9162510848,"remaining_time":2.179191769},
{"learn":[95614.20699],"iteration":296,"passed_time":0.9190987127,"remaining_time":2.175509748},
{"learn":[95582.3628],"iteration":297,"passed_time":0.9221856345,"remaining_time":2.172397032},
{"learn":[95563.98743],"iteration":298,"passed_time":0.9248092773,"remaining_time":2.168198339},
{"learn":[95528.89116],"iteration":299,"passed_time":0.9274551893,"remaining_time":2.164062108},
{"learn":[95513.43177],"iteration":300,"passed_time":0.9300637132,"remaining_time":2.159848955},
{"learn":[95464.4089],"iteration":301,"passed_time":0.9330462385,"remaining_time":2.156510843},
{"learn":[95441.43832],"iteration":302,"passed_time":0.9359040024,"remaining_time":2.152888085},
{"learn":[95386.14686],"iteration":303,"passed_time":0.9388871855,"remaining_time":2.149557504},
{"learn":[95345.12592],"iteration":304,"passed_time":0.9417265976,"remaining_time":2.145901591},
{"learn":[95298.4664],"iteration":305,"passed_time":0.9445837994,"remaining_time":2.142291362},
{"learn":[95265.67162],"iteration":306,"passed_time":0.9476494893,"remaining_time":2.139156665},
{"learn":[95241.0322],"iteration":307,"passed_time":0.9506974705,"remaining_time":2.135982629},
{"learn":[95219.52581],"iteration":308,"passed_time":0.9538234853,"remaining_time":2.13298391},
{"learn":[95201.39216],"iteration":309,"passed_time":0.9564931178,"remaining_time":2.128968552},
{"learn":[95180.38858],"iteration":310,"passed_time":0.9591426628,"remaining_time":2.124917346},
{"learn":[95152.33934],"iteration":311,"passed_time":0.9617642493,"remaining_time":2.120813473},
{"learn":[95095.39771],"iteration":312,"passed_time":0.9647848727,"remaining_time":2.117594912},
{"learn":[95081.0872],"iteration":313,"passed_time":0.9676198287,"remaining_time":2.113971982},
{"learn":[95066.65042],"iteration":314,"passed_time":0.97042878,"remaining_time":2.110297506},
{"learn":[95020.39689],"iteration":315,"passed_time":0.9731992549,"remaining_time":2.106545223},
{"learn":[95001.22549],"iteration":316,"passed_time":0.9763614297,"remaining_time":2.10364308},
{"learn":[94955.37082],"iteration":317,"passed_time":0.9802002561,"remaining_time":2.102190486},
{"learn":[94944.2243],"iteration":318,"passed_time":0.9840027417,"remaining_time":2.100645351},
{"learn":[94910.12197],"iteration":319,"passed_time":0.9884942598,"remaining_time":2.100550302},
{"learn":[94873.94251],"iteration":320,"passed_time":0.9922964182,"remaining_time":2.098969682},
{"learn":[94854.14333],"iteration":321,"passed_time":0.9967574398,"remaining_time":2.09876256},
{"learn":[94809.06104],"iteration":322,"passed_time":1.000433204,"remaining_time":2.096883217},
{"learn":[94734.01216],"iteration":323,"passed_time":1.00388727,"remaining_time":2.094530229},
{"learn":[94707.29218],"iteration":324,"passed_time":1.007347557,"remaining_time":2.092183388},
{"learn":[94674.18182],"iteration":325,"passed_time":1.010584318,"remaining_time":2.089367578},
{"learn":[94669.21618],"iteration":326,"passed_time":1.013829052,"remaining_time":2.086565602},
{"learn":[94632.43609],"iteration":327,"passed_time":1.017300788,"remaining_time":2.084226004},
{"learn":[94588.96501],"iteration":328,"passed_time":1.020478962,"remaining_time":2.081280801},
{"learn":[94568.62367],"iteration":329,"passed_time":1.023516606,"remaining_time":2.078048866},
{"learn":[94525.13824],"iteration":330,"passed_time":1.026703764,"remaining_time":2.075120296},
{"learn":[94523.74052],"iteration":331,"passed_time":1.028881291,"remaining_time":2.070158742},
{"learn":[94480.67447],"iteration":332,"passed_time":1.032288706,"remaining_time":2.067677377},
{"learn":[94433.25658],"iteration":333,"passed_time":1.035196887,"remaining_time":2.064194991},
{"learn":[94409.87873],"iteration":334,"passed_time":1.03823873,"remaining_time":2.06098136},
{"learn":[94397.47073],"iteration":335,"passed_time":1.041057932,"remaining_time":2.057328771},
{"learn":[94376.8237],"iteration":336,"passed_time":1.04480591,"remaining_time":2.055508362},
{"learn":[94331.98939],"iteration":337,"passed_time":1.047992655,"remaining_time":2.05257733},
{"learn":[94281.69034],"iteration":338,"passed_time":1.0516344,"remaining_time":2.050531971},
{"learn":[94247.94418],"iteration":339,"passed_time":1.054675758,"remaining_time":2.047311765},
{"learn":[94211.5879],"iteration":340,"passed_time":1.058775605,"remaining_time":2.046138192},
{"learn":[94198.32588],"iteration":341,"passed_time":1.062252858,"remaining_time":2.043749651},
{"learn":[94154.43913],"iteration":342,"passed_time":1.065376514,"remaining_time":2.040677463},
{"learn":[94123.39505],"iteration":343,"passed_time":1.068431276,"remaining_time":2.037473596},
{"learn":[94090.70412],"iteration":344,"passed_time":1.071565615,"remaining_time":2.034421675},
{"learn":[94074.29444],"iteration":345,"passed_time":1.074666103,"remaining_time":2.031305293},
{"learn":[94021.32959],"iteration":346,"passed_time":1.078331966,"remaining_time":2.02925295},
{"learn":[93979.75284],"iteration":347,"passed_time":1.081417311,"remaining_time":2.026103697},
{"learn":[93942.01663],"iteration":348,"passed_time":1.084569171,"remaining_time":2.023078883},
{"learn":[93894.86227],"iteration":349,"passed_time":1.088083088,"remaining_time":2.020725734},
{"learn":[93866.41463],"iteration":350,"passed_time":1.091140744,"remaining_time":2.017522345},
{"learn":[93832.81061],"iteration":351,"passed_time":1.094848731,"remaining_time":2.015516983},
{"learn":[93800.59121],"iteration":352,"passed_time":1.098265777,"remaining_time":2.012968719},
{"learn":[93770.93741],"iteration":353,"passed_time":1.101514432,"remaining_time":2.010108256},
{"learn":[93745.77449],"iteration":354,"passed_time":1.104659104,"remaining_time":2.007056682},
{"learn":[93706.59937],"iteration":355,"passed_time":1.107803989,"remaining_time":2.004004969},
{"learn":[93668.70246],"iteration":356,"passed_time":1.111065223,"remaining_time":2.001162293},
{"learn":[93644.97076],"iteration":357,"passed_time":1.114454897,"remaining_time":1.998547608},
{"learn":[93619.40306],"iteration":358,"passed_time":1.117601927,"remaining_time":1.995495363},
{"learn":[93579.33302],"iteration":359,"passed_time":1.120485112,"remaining_time":1.991973532},
{"learn":[93562.27994],"iteration":360,"passed_time":1.123536703,"remaining_time":1.988753334},
{"learn":[93542.43044],"iteration":361,"passed_time":1.127000364,"remaining_time":1.986260311},
{"learn":[93503.24933],"iteration":362,"passed_time":1.130273985,"remaining_time":1.983428453},
{"learn":[93474.82279],"iteration":363,"passed_time":1.133610576,"remaining_time":1.980704193},
{"learn":[93441.86227],"iteration":364,"passed_time":1.136996581,"remaining_time":1.978062545},
{"learn":[93390.97153],"iteration":365,"passed_time":1.140156442,"remaining_time":1.975025094},
{"learn":[93374.51489],"iteration":366,"passed_time":1.143520848,"remaining_time":1.972339774},
{"learn":[93350.82226],"iteration":367,"passed_time":1.147068201,"remaining_time":1.969964953},
{"learn":[93323.02573],"iteration":368,"passed_time":1.151725872,"remaining_time":1.969482453},
{"learn":[93302.58034],"iteration":369,"passed_time":1.154917061,"remaining_time":1.966480401},
{"learn":[93294.36127],"iteration":370,"passed_time":1.157976261,"remaining_time":1.963253553},
{"learn":[93272.13747],"iteration":371,"passed_time":1.161172839,"remaining_time":1.960259524},
{"learn":[93227.99884],"iteration":372,"passed_time":1.164964502,"remaining_time":1.958264726},
{"learn":[93217.68563],"iteration":373,"passed_time":1.167617137,"remaining_time":1.954353817},
{"learn":[93197.39171],"iteration":374,"passed_time":1.170401889,"remaining_time":1.950669815},
{"learn":[93168.23266],"iteration":375,"passed_time":1.173659148,"remaining_time":1.947774757},
{"learn":[93130.49698],"iteration":376,"passed_time":1.176703726,"remaining_time":1.944526317},
{"learn":[93106.90193],"iteration":377,"passed_time":1.179894012,"remaining_time":1.941518719},
{"learn":[93074.34734],"iteration":378,"passed_time":1.182902999,"remaining_time":1.938213093},
{"learn":[93051.34079],"iteration":379,"passed_time":1.185613322,"remaining_time":1.934421736},
{"learn":[93031.68415],"iteration":380,"passed_time":1.188503598,"remaining_time":1.930928417},
{"learn":[93015.76543],"iteration":381,"passed_time":1.191499266,"remaining_time":1.927608761},
{"learn":[93006.43472],"iteration":382,"passed_time":1.194777802,"remaining_time":1.924746486},
{"learn":[92978.65277],"iteration":383,"passed_time":1.197456948,"remaining_time":1.92092052},
{"learn":[92951.03162],"iteration":384,"passed_time":1.20019736,"remaining_time":1.91719838},
{"learn":[92920.97032],"iteration":385,"passed_time":1.202911932,"remaining_time":1.913440224},
{"learn":[92882.88767],"iteration":386,"passed_time":1.205963647,"remaining_time":1.910221487},
{"learn":[92858.29862],"iteration":387,"passed_time":1.209293408,"remaining_time":1.90744218},
{"learn":[92831.93035],"iteration":388,"passed_time":1.212198218,"remaining_time":1.903992574},
{"learn":[92803.03791],"iteration":389,"passed_time":1.214908924,"remaining_time":1.900242163},
{"learn":[92775.33799],"iteration":390,"passed_time":1.217584642,"remaining_time":1.896442575},
{"learn":[92749.95002],"iteration":391,"passed_time":1.220312222,"remaining_time":1.892729161},
{"learn":[92714.31991],"iteration":392,"passed_time":1.223317473,"remaining_time":1.889449634},
{"learn":[92693.31483],"iteration":393,"passed_time":1.226199446,"remaining_time":1.885981888},
{"learn":[92686.96913],"iteration":394,"passed_time":1.228788631,"remaining_time":1.882068663},
{"learn":[92655.59306],"iteration":395,"passed_time":1.231593431,"remaining_time":1.878490991},
{"learn":[92626.83224],"iteration":396,"passed_time":1.234364986,"remaining_time":1.874866717},
{"learn":[92598.92388],"iteration":397,"passed_time":1.237510019,"remaining_time":1.871811637},
{"learn":[92564.31405],"iteration":398,"passed_time":1.241135136,"remaining_time":1.86947924},
{"learn":[92540.88557],"iteration":399,"passed_time":1.244367299,"remaining_time":1.866550949},
{"learn":[92530.06649],"iteration":400,"passed_time":1.247409349,"remaining_time":1.863337158},
{"learn":[92490.89848],"iteration":401,"passed_time":1.250548479,"remaining_time":1.860268632},
{"learn":[92447.42717],"iteration":402,"passed_time":1.254202231,"remaining_time":1.857962115},
{"learn":[92438.3805],"iteration":403,"passed_time":1.257691104,"remaining_time":1.855405688},
{"learn":[92417.14292],"iteration":404,"passed_time":1.261076462,"remaining_time":1.85269258},
{"learn":[92404.9109],"iteration":405,"passed_time":1.263990867,"remaining_time":1.849287131},
{"learn":[92367.89349],"iteration":406,"passed_time":1.267482553,"remaining_time":1.846725193},
{"learn":[92326.53922],"iteration":407,"passed_time":1.27099394,"remaining_time":1.844187286},
{"learn":[92313.30689],"iteration":408,"passed_time":1.273836227,"remaining_time":1.840677776},
{"learn":[92272.77377],"iteration":409,"passed_time":1.277317972,"remaining_time":1.838091716},
{"learn":[92252.09844],"iteration":410,"passed_time":1.280082863,"remaining_time":1.834473982},
{"learn":[92228.08821],"iteration":411,"passed_time":1.283706234,"remaining_time":1.832085597},
{"learn":[92222.36854],"iteration":412,"passed_time":1.287210582,"remaining_time":1.829522062},
{"learn":[92191.67457],"iteration":413,"passed_time":1.290590291,"remaining_time":1.826777562},
{"learn":[92160.32912],"iteration":414,"passed_time":1.29388794,"remaining_time":1.823914324},
{"learn":[92119.80492],"iteration":415,"passed_time":1.29696077,"remaining_time":1.820733388},
{"learn":[92093.58545],"iteration":416,"passed_time":1.300292902,"remaining_time":1.817915496},
{"learn":[92075.52764],"iteration":417,"passed_time":1.303343751,"remaining_time":1.814703501},
{"learn":[92057.85693],"iteration":418,"passed_time":1.306513914,"remaining_time":1.811657719},
{"learn":[92022.70472],"iteration":419,"passed_time":1.31079854,"remaining_time":1.810150365},
{"learn":[91988.58596],"iteration":420,"passed_time":1.314342876,"remaining_time":1.807611699},
{"learn":[91952.40285],"iteration":421,"passed_time":1.318009895,"remaining_time":1.805236301},
{"learn":[91914.33384],"iteration":422,"passed_time":1.321317562,"remaining_time":1.802364617},
{"learn":[91889.90697],"iteration":423,"passed_time":1.324653123,"remaining_time":1.799528771},
{"learn":[91860.89274],"iteration":424,"passed_time":1.327874289,"remaining_time":1.796535802},
{"learn":[91841.40401],"iteration":425,"passed_time":1.331052319,"remaining_time":1.793483641},
{"learn":[91816.69444],"iteration":426,"passed_time":1.334240933,"remaining_time":1.790445093},
{"learn":[91806.71749],"iteration":427,"passed_time":1.337538537,"remaining_time":1.787551503},
{"learn":[91788.96799],"iteration":428,"passed_time":1.340875481,"remaining_time":1.784708391},
{"learn":[91757.51388],"iteration":429,"passed_time":1.344395529,"remaining_time":1.782105701},
{"learn":[91737.5986],"iteration":430,"passed_time":1.347474873,"remaining_time":1.778916944},
{"learn":[91697.51845],"iteration":431,"passed_time":1.351098285,"remaining_time":1.776444042},
{"learn":[91666.85079],"iteration":432,"passed_time":1.354173547,"remaining_time":1.773248039},
{"learn":[91643.59238],"iteration":433,"passed_time":1.357778626,"remaining_time":1.770743553},
{"learn":[91572.01738],"iteration":434,"passed_time":1.360988643,"remaining_time":1.767720881},
{"learn":[91548.5562],"iteration":435,"passed_time":1.363946405,"remaining_time":1.764371038},
{"learn":[91524.08527],"iteration":436,"passed_time":1.367475293,"remaining_time":1.761758788},
{"learn":[91508.66202],"iteration":437,"passed_time":1.370740555,"remaining_time":1.758804091},
{"learn":[91468.85211],"iteration":438,"passed_time":1.374641722,"remaining_time":1.756660606},
{"learn":[91436.08577],"iteration":439,"passed_time":1.377638338,"remaining_time":1.753357885},
{"learn":[91413.27933],"iteration":440,"passed_time":1.380641823,"remaining_time":1.750065259},
{"learn":[91391.87747],"iteration":441,"passed_time":1.383864465,"remaining_time":1.747050614},
{"learn":[91361.46575],"iteration":442,"passed_time":1.387045584,"remaining_time":1.743982823},
{"learn":[91358.13022],"iteration":443,"passed_time":1.390267313,"remaining_time":1.740965374},
{"learn":[91320.00579],"iteration":444,"passed_time":1.393524014,"remaining_time":1.737990624},
{"learn":[91282.00405],"iteration":445,"passed_time":1.396597237,"remaining_time":1.734786703},
{"learn":[91263.95829],"iteration":446,"passed_time":1.400107613,"remaining_time":1.732124184},
{"learn":[91229.7517],"iteration":447,"passed_time":1.403525457,"remaining_time":1.729343867},
{"learn":[91209.32934],"iteration":448,"passed_time":1.406515119,"remaining_time":1.726035258},
{"learn":[91185.91786],"iteration":449,"passed_time":1.409239343,"remaining_time":1.722403642},
{"learn":[91165.14749],"iteration":450,"passed_time":1.411935791,"remaining_time":1.718742238},
{"learn":[91154.51739],"iteration":451,"passed_time":1.41449825,"remaining_time":1.714922657},
{"learn":[91135.74899],"iteration":452,"passed_time":1.417305566,"remaining_time":1.711404293},
{"learn":[91115.61315],"iteration":453,"passed_time":1.42042528,"remaining_time":1.708264765},
{"learn":[91061.23111],"iteration":454,"passed_time":1.423083422,"remaining_time":1.70457245},
{"learn":[91043.02792],"iteration":455,"passed_time":1.425799142,"remaining_time":1.700953362},
{"learn":[91025.53866],"iteration":456,"passed_time":1.428312938,"remaining_time":1.697098305},
{"learn":[91018.09603],"iteration":457,"passed_time":1.430991088,"remaining_time":1.693443602},
{"learn":[90993.03231],"iteration":458,"passed_time":1.434108233,"remaining_time":1.690310576},
{"learn":[90963.51234],"iteration":459,"passed_time":1.437290656,"remaining_time":1.687254248},
{"learn":[90930.5395],"iteration":460,"passed_time":1.440221738,"remaining_time":1.683903507},
{"learn":[90916.44573],"iteration":461,"passed_time":1.442942644,"remaining_time":1.680309832},
{"learn":[90873.489],"iteration":462,"passed_time":1.44597435,"remaining_time":1.677080401},
{"learn":[90851.63908],"iteration":463,"passed_time":1.449395742,"remaining_time":1.674301978},
{"learn":[90815.59549],"iteration":464,"passed_time":1.452805251,"remaining_time":1.671507117},
{"learn":[90791.19994],"iteration":465,"passed_time":1.455609746,"remaining_time":1.668016319},
{"learn":[90770.67381],"iteration":466,"passed_time":1.458298814,"remaining_time":1.664396719},
{"learn":[90770.01635],"iteration":467,"passed_time":1.459931012,"remaining_time":1.659579697},
{"learn":[90745.06692],"iteration":468,"passed_time":1.462903702,"remaining_time":1.656293957},
{"learn":[90707.33474],"iteration":469,"passed_time":1.466285063,"remaining_time":1.65347039},
{"learn":[90680.35223],"iteration":470,"passed_time":1.469342298,"remaining_time":1.650280416},
{"learn":[90651.23206],"iteration":471,"passed_time":1.472890677,"remaining_time":1.647640419},
{"learn":[90618.44077],"iteration":472,"passed_time":1.475614543,"remaining_time":1.644077936},
{"learn":[90577.09857],"iteration":473,"passed_time":1.478406677,"remaining_time":1.640594751},
{"learn":[90557.3235],"iteration":474,"passed_time":1.481939077,"remaining_time":1.637932664},
{"learn":[90534.16056],"iteration":475,"passed_time":1.485193714,"remaining_time":1.634961147},
{"learn":[90514.02484],"iteration":476,"passed_time":1.488075837,"remaining_time":1.631580006},
{"learn":[90503.52644],"iteration":477,"passed_time":1.4908843,"remaining_time":1.628120511},
{"learn":[90471.6532],"iteration":478,"passed_time":1.493806089,"remaining_time":1.624786999},
{"learn":[90441.45702],"iteration":479,"passed_time":1.497640367,"remaining_time":1.622443731},
{"learn":[90419.85278],"iteration":480,"passed_time":1.500759648,"remaining_time":1.61932278},
{"learn":[90390.06896],"iteration":481,"passed_time":1.503760755,"remaining_time":1.616074836},
{"learn":[90352.37106],"iteration":482,"passed_time":1.506453731,"remaining_time":1.612498093},
{"learn":[90317.31769],"iteration":483,"passed_time":1.509275254,"remaining_time":1.609062048},
{"learn":[90285.70503],"iteration":484,"passed_time":1.512759471,"remaining_time":1.606332222},
{"learn":[90264.09319],"iteration":485,"passed_time":1.515651769,"remaining_time":1.60297327},
{"learn":[90234.21243],"iteration":486,"passed_time":1.518661779,"remaining_time":1.599740231},
{"learn":[90199.55059],"iteration":487,"passed_time":1.521517221,"remaining_time":1.596345937},
{"learn":[90176.5909],"iteration":488,"passed_time":1.524424659,"remaining_time":1.593008181},
{"learn":[90151.02095],"iteration":489,"passed_time":1.527706716,"remaining_time":1.590062092},
{"learn":[90126.67704],"iteration":490,"passed_time":1.530986914,"remaining_time":1.587112707},
{"learn":[90106.38096],"iteration":491,"passed_time":1.533863003,"remaining_time":1.583744726},
{"learn":[90083.96037],"iteration":492,"passed_time":1.536770747,"remaining_time":1.580411296},
{"learn":[90066.04737],"iteration":493,"passed_time":1.539939512,"remaining_time":1.57734695},
{"learn":[90040.3166],"iteration":494,"passed_time":1.543016948,"remaining_time":1.574189007},
{"learn":[90019.25537],"iteration":495,"passed_time":1.546138611,"remaining_time":1.571076331},
{"learn":[89981.75808],"iteration":496,"passed_time":1.549102133,"remaining_time":1.567803567},
{"learn":[89945.89355],"iteration":497,"passed_time":1.552043236,"remaining_time":1.564509447},
{"learn":[89914.54308],"iteration":498,"passed_time":1.55502041,"remaining_time":1.561252957},
{"learn":[89892.57663],"iteration":499,"passed_time":1.557979758,"remaining_time":1.557979758},
{"learn":[89876.59809],"iteration":500,"passed_time":1.561112303,"remaining_time":1.554880317},
{"learn":[89848.93388],"iteration":501,"passed_time":1.564011355,"remaining_time":1.551549113},
{"learn":[89821.83181],"iteration":502,"passed_time":1.567193804,"remaining_time":1.548499644},
{"learn":[89788.45972],"iteration":503,"passed_time":1.570282738,"remaining_time":1.545357615},
{"learn":[89767.30577],"iteration":504,"passed_time":1.573449887,"remaining_time":1.542292463},
{"learn":[89751.27252],"iteration":505,"passed_time":1.576710489,"remaining_time":1.539318146},
{"learn":[89728.03148],"iteration":506,"passed_time":1.579689528,"remaining_time":1.53606891},
{"learn":[89710.67889],"iteration":507,"passed_time":1.582667492,"remaining_time":1.532819697},
{"learn":[89688.40805],"iteration":508,"passed_time":1.586058703,"remaining_time":1.529970183},
{"learn":[89655.2093],"iteration":509,"passed_time":1.589589968,"remaining_time":1.527253106},
{"learn":[89631.36006],"iteration":510,"passed_time":1.592894545,"remaining_time":1.524315915},
{"learn":[89627.19664],"iteration":511,"passed_time":1.595853401,"remaining_time":1.521047773},
{"learn":[89602.6895],"iteration":512,"passed_time":1.599199349,"remaining_time":1.51814831},
{"learn":[89579.53038],"iteration":513,"passed_time":1.602846504,"remaining_time":1.515531909},
{"learn":[89558.73639],"iteration":514,"passed_time":1.605888536,"remaining_time":1.512341631},
{"learn":[89522.68556],"iteration":515,"passed_time":1.609026772,"remaining_time":1.509242166},
{"learn":[89487.79547],"iteration":516,"passed_time":1.612248752,"remaining_time":1.506220788},
{"learn":[89487.24905],"iteration":517,"passed_time":1.614141919,"remaining_time":1.501962172},
{"learn":[89467.89235],"iteration":518,"passed_time":1.61735587,"remaining_time":1.49893675},
{"learn":[89457.51863],"iteration":519,"passed_time":1.620370157,"remaining_time":1.495726299},
{"learn":[89441.06374],"iteration":520,"passed_time":1.623222544,"remaining_time":1.492367752},
{"learn":[89434.43739],"iteration":521,"passed_time":1.626419549,"remaining_time":1.489326713},
{"learn":[89399.90128],"iteration":522,"passed_time":1.629814866,"remaining_time":1.486465949},
{"learn":[89376.12898],"iteration":523,"passed_time":1.633888166,"remaining_time":1.484219021},
{"learn":[89348.74449],"iteration":524,"passed_time":1.637276563,"remaining_time":1.481345462},
{"learn":[89318.29925],"iteration":525,"passed_time":1.640455886,"remaining_time":1.47828154},
{"learn":[89301.79471],"iteration":526,"passed_time":1.643840258,"remaining_time":1.475401218},
{"learn":[89275.9501],"iteration":527,"passed_time":1.647406817,"remaining_time":1.472681852},
{"learn":[89262.10786],"iteration":528,"passed_time":1.650300637,"remaining_time":1.469360302},
{"learn":[89238.04242],"iteration":529,"passed_time":1.6533656,"remaining_time":1.466192136},
{"learn":[89201.46354],"iteration":530,"passed_time":1.656591643,"remaining_time":1.46316663},
{"learn":[89178.6869],"iteration":531,"passed_time":1.659675942,"remaining_time":1.460015678},
{"learn":[89149.09243],"iteration":532,"passed_time":1.66371698,"remaining_time":1.457703245},
{"learn":[89118.95572],"iteration":533,"passed_time":1.666947453,"remaining_time":1.454676991},
{"learn":[89091.36513],"iteration":534,"passed_time":1.669903182,"remaining_time":1.451411177},
{"learn":[89080.18368],"iteration":535,"passed_time":1.672974545,"remaining_time":1.448246621},
{"learn":[89062.62742],"iteration":536,"passed_time":1.676590263,"remaining_time":1.445551754},
{"learn":[89031.85533],"iteration":537,"passed_time":1.680132674,"remaining_time":1.442790512},
{"learn":[89014.99525],"iteration":538,"passed_time":1.683532059,"remaining_time":1.439904043},
{"learn":[88976.91126],"iteration":539,"passed_time":1.686461804,"remaining_time":1.436615611},
{"learn":[88968.16407],"iteration":540,"passed_time":1.689463177,"remaining_time":1.433389276},
{"learn":[88943.9119],"iteration":541,"passed_time":1.693255208,"remaining_time":1.430831892},
{"learn":[88923.6055],"iteration":542,"passed_time":1.696604537,"remaining_time":1.427897372},
{"learn":[88916.70903],"iteration":543,"passed_time":1.699569884,"remaining_time":1.424639461},
{"learn":[88894.2941],"iteration":544,"passed_time":1.702571654,"remaining_time":1.421413032},
{"learn":[88880.68246],"iteration":545,"passed_time":1.705812659,"remaining_time":1.41838635},
{"learn":[88874.36925],"iteration":546,"passed_time":1.709064166,"remaining_time":1.415367582},
{"learn":[88847.89159],"iteration":547,"passed_time":1.71252516,"remaining_time":1.412520753},
{"learn":[88824.19612],"iteration":548,"passed_time":1.715779515,"remaining_time":1.409501933},
{"learn":[88809.00164],"iteration":549,"passed_time":1.718673038,"remaining_time":1.406187031},
{"learn":[88779.28736],"iteration":550,"passed_time":1.722218214,"remaining_time":1.403404679},
{"learn":[88751.25859],"iteration":551,"passed_time":1.72586045,"remaining_time":1.400698336},
{"learn":[88728.84735],"iteration":552,"passed_time":1.730024274,"remaining_time":1.398410218},
{"learn":[88698.71419],"iteration":553,"passed_time":1.733454016,"remaining_time":1.395524352},
{"learn":[88668.86961],"iteration":554,"passed_time":1.736408747,"remaining_time":1.392255662},
{"learn":[88646.46584],"iteration":555,"passed_time":1.73976928,"remaining_time":1.389312159},
{"learn":[88621.11136],"iteration":556,"passed_time":1.742761215,"remaining_time":1.386074},
{"learn":[88606.38277],"iteration":557,"passed_time":1.745504399,"remaining_time":1.382639685},
{"learn":[88591.76445],"iteration":558,"passed_time":1.748137119,"remaining_time":1.379120696},
{"learn":[88574.90607],"iteration":559,"passed_time":1.750671082,"remaining_time":1.375527279},
{"learn":[88556.58327],"iteration":560,"passed_time":1.753759927,"remaining_time":1.37237185},
{"learn":[88532.34951],"iteration":561,"passed_time":1.75661532,"remaining_time":1.369034716},
{"learn":[88503.95835],"iteration":562,"passed_time":1.759644522,"remaining_time":1.365834203},
{"learn":[88491.45116],"iteration":563,"passed_time":1.762317363,"remaining_time":1.362358812},
{"learn":[88474.26692],"iteration":564,"passed_time":1.765021416,"remaining_time":1.358910294},
{"learn":[88463.19921],"iteration":565,"passed_time":1.767954808,"remaining_time":1.355640259},
{"learn":[88445.58596],"iteration":566,"passed_time":1.771030606,"remaining_time":1.352480163},
{"learn":[88416.35984],"iteration":567,"passed_time":1.774021145,"remaining_time":1.349255519},
{"learn":[88397.08466],"iteration":568,"passed_time":1.777603525,"remaining_time":1.346479999},
{"learn":[88368.71587],"iteration":569,"passed_time":1.780353502,"remaining_time":1.343073694},
{"learn":[88354.29381],"iteration":570,"passed_time":1.783568173,"remaining_time":1.34001882},
{"learn":[88337.38874],"iteration":571,"passed_time":1.786402312,"remaining_time":1.336678653},
{"learn":[88312.23428],"iteration":572,"passed_time":1.789218835,"remaining_time":1.333327125},
{"learn":[88288.70672],"iteration":573,"passed_time":1.792509062,"remaining_time":1.330329025},
{"learn":[88270.42153],"iteration":574,"passed_time":1.795609584,"remaining_time":1.327189693},
{"learn":[88237.91252],"iteration":575,"passed_time":1.798569062,"remaining_time":1.323946671},
{"learn":[88225.18415],"iteration":576,"passed_time":1.801256924,"remaining_time":1.320505509},
{"learn":[88204.32575],"iteration":577,"passed_time":1.80435747,"remaining_time":1.317368256},
{"learn":[88185.35965],"iteration":578,"passed_time":1.807546432,"remaining_time":1.31429542},
{"learn":[88172.64133],"iteration":579,"passed_time":1.810183984,"remaining_time":1.310822885},
{"learn":[88152.58838],"iteration":580,"passed_time":1.813365621,"remaining_time":1.307745603},
{"learn":[88130.19947],"iteration":581,"passed_time":1.816038653,"remaining_time":1.304302675},
{"learn":[88113.22717],"iteration":582,"passed_time":1.819165446,"remaining_time":1.301186948},
{"learn":[88088.36272],"iteration":583,"passed_time":1.822081258,"remaining_time":1.297920896},
{"learn":[88056.13027],"iteration":584,"passed_time":1.825242674,"remaining_time":1.294830273},
{"learn":[88034.41872],"iteration":585,"passed_time":1.828312315,"remaining_time":1.29167457},
{"learn":[88021.63146],"iteration":586,"passed_time":1.831155466,"remaining_time":1.288359808},
{"learn":[87994.85345],"iteration":587,"passed_time":1.833944251,"remaining_time":1.285008557},
{"learn":[87971.93858],"iteration":588,"passed_time":1.836803623,"remaining_time":1.28170847},
{"learn":[87957.01359],"iteration":589,"passed_time":1.839569426,"remaining_time":1.278344856},
{"learn":[87938.10851],"iteration":590,"passed_time":1.842406434,"remaining_time":1.275032541},
{"learn":[87923.59114],"iteration":591,"passed_time":1.845322576,"remaining_time":1.27177637},
{"learn":[87898.01263],"iteration":592,"passed_time":1.848083168,"remaining_time":1.268414586},
{"learn":[87880.45892],"iteration":593,"passed_time":1.850949363,"remaining_time":1.265127005},
{"learn":[87864.52574],"iteration":594,"passed_time":1.853842575,"remaining_time":1.261859232},
{"learn":[87846.59223],"iteration":595,"passed_time":1.856743603,"remaining_time":1.258598013},
{"learn":[87827.74102],"iteration":596,"passed_time":1.860318834,"remaining_time":1.255793116},
{"learn":[87815.32706],"iteration":597,"passed_time":1.863514545,"remaining_time":1.252730513},
{"learn":[87799.52522],"iteration":598,"passed_time":1.866693474,"remaining_time":1.249656232},
{"learn":[87772.07051],"iteration":599,"passed_time":1.870133959,"remaining_time":1.246755973},
{"learn":[87748.65753],"iteration":600,"passed_time":1.873294086,"remaining_time":1.243667788},
{"learn":[87725.53724],"iteration":601,"passed_time":1.876528655,"remaining_time":1.240628579},
{"learn":[87716.89033],"iteration":602,"passed_time":1.879390256,"remaining_time":1.23734317},
{"learn":[87693.5219],"iteration":603,"passed_time":1.88221623,"remaining_time":1.234035806},
{"learn":[87668.73913],"iteration":604,"passed_time":1.885536822,"remaining_time":1.231052966},
{"learn":[87652.0003],"iteration":605,"passed_time":1.888434586,"remaining_time":1.227794104},
{"learn":[87633.58377],"iteration":606,"passed_time":1.891703699,"remaining_time":1.22477686},
{"learn":[87610.98949],"iteration":607,"passed_time":1.894511343,"remaining_time":1.221461261},
{"learn":[87594.42877],"iteration":608,"passed_time":1.897330608,"remaining_time":1.218154791},
{"learn":[87571.00516],"iteration":609,"passed_time":1.900502331,"remaining_time":1.215075261},
{"learn":[87550.85303],"iteration":610,"passed_time":1.903337619,"remaining_time":1.211781233},
{"learn":[87520.62342],"iteration":611,"passed_time":1.906835613,"remaining_time":1.208908853},
{"learn":[87505.5472],"iteration":612,"passed_time":1.909586915,"remaining_time":1.205563028},
{"learn":[87486.89784],"iteration":613,"passed_time":1.912425922,"remaining_time":1.202274277},
{"learn":[87455.02035],"iteration":614,"passed_time":1.915567995,"remaining_time":1.199176712},
{"learn":[87428.51924],"iteration":615,"passed_time":1.918538534,"remaining_time":1.195972073},
{"learn":[87413.92013],"iteration":616,"passed_time":1.922238925,"remaining_time":1.193221245},
{"learn":[87399.35981],"iteration":617,"passed_time":1.925340535,"remaining_time":1.190097224},
{"learn":[87378.0908],"iteration":618,"passed_time":1.928249751,"remaining_time":1.186854855},
{"learn":[87359.03369],"iteration":619,"passed_time":1.931087305,"remaining_time":1.183569639},
{"learn":[87342.22921],"iteration":620,"passed_time":1.93426191,"remaining_time":1.180491568},
{"learn":[87330.98539],"iteration":621,"passed_time":1.937769662,"remaining_time":1.177615647},
{"learn":[87316.30771],"iteration":622,"passed_time":1.940600355,"remaining_time":1.174327984},
{"learn":[87295.35008],"iteration":623,"passed_time":1.943253254,"remaining_time":1.170934653},
{"learn":[87265.55278],"iteration":624,"passed_time":1.945977131,"remaining_time":1.167586278},
{"learn":[87254.09868],"iteration":625,"passed_time":1.948963057,"remaining_time":1.164396459},
{"learn":[87242.32709],"iteration":626,"passed_time":1.95210341,"remaining_time":1.161299158},
{"learn":[87223.93847],"iteration":627,"passed_time":1.956007086,"remaining_time":1.158653879},
{"learn":[87205.26022],"iteration":628,"passed_time":1.95924164,"remaining_time":1.155609934},
{"learn":[87181.0967],"iteration":629,"passed_time":1.962751751,"remaining_time":1.152727219},
{"learn":[87157.206],"iteration":630,"passed_time":1.965819093,"remaining_time":1.14958359},
{"learn":[87141.82688],"iteration":631,"passed_time":1.96948073,"remaining_time":1.146786248},
{"learn":[87119.92611],"iteration":632,"passed_time":1.972310617,"remaining_time":1.143503944},
{"learn":[87089.90002],"iteration":633,"passed_time":1.975519015,"remaining_time":1.140441577},
{"learn":[87066.05049],"iteration":634,"passed_time":1.978487049,"remaining_time":1.137240587},
{"learn":[87053.0002],"iteration":635,"passed_time":1.98203215,"remaining_time":1.134370601},
{"learn":[87028.19371],"iteration":636,"passed_time":1.985814663,"remaining_time":1.131633788},
{"learn":[87012.02619],"iteration":637,"passed_time":1.989254018,"remaining_time":1.128698989},
{"learn":[86990.09421],"iteration":638,"passed_time":1.992429901,"remaining_time":1.125613763},
{"learn":[86971.59318],"iteration":639,"passed_time":1.995674859,"remaining_time":1.122567108},
{"learn":[86952.84678],"iteration":640,"passed_time":1.999182601,"remaining_time":1.119667011},
{"learn":[86936.2801],"iteration":641,"passed_time":2.002485456,"remaining_time":1.116650768},
{"learn":[86927.4952],"iteration":642,"passed_time":2.005576073,"remaining_time":1.113515798},
{"learn":[86905.45868],"iteration":643,"passed_time":2.008524739,"remaining_time":1.110302496},
{"learn":[86892.35575],"iteration":644,"passed_time":2.011484406,"remaining_time":1.107096069},
{"learn":[86881.08927],"iteration":645,"passed_time":2.015046719,"remaining_time":1.104220648},
{"learn":[86864.84231],"iteration":646,"passed_time":2.018413014,"remaining_time":1.101236157},
{"learn":[86844.50063],"iteration":647,"passed_time":2.021873707,"remaining_time":1.098301767},
{"learn":[86828.23627],"iteration":648,"passed_time":2.025086527,"remaining_time":1.095231696},
{"learn":[86802.87291],"iteration":649,"passed_time":2.028943522,"remaining_time":1.09250805},
{"learn":[86788.00379],"iteration":650,"passed_time":2.032412693,"remaining_time":1.089573011},
{"learn":[86764.21405],"iteration":651,"passed_time":2.035884285,"remaining_time":1.086637624},
{"learn":[86748.83157],"iteration":652,"passed_time":2.038719703,"remaining_time":1.083362537},
{"learn":[86729.95999],"iteration":653,"passed_time":2.041618272,"remaining_time":1.080122205},
{"learn":[86709.52185],"iteration":654,"passed_time":2.045275634,"remaining_time":1.077282586},
{"learn":[86688.39574],"iteration":655,"passed_time":2.048527589,"remaining_time":1.074227882},
{"learn":[86675.30755],"iteration":656,"passed_time":2.051699722,"remaining_time":1.071130905},
{"learn":[86649.55148],"iteration":657,"passed_time":2.054437271,"remaining_time":1.067807821},
{"learn":[86621.85874],"iteration":658,"passed_time":2.0572269,"remaining_time":1.064513464},
{"learn":[86604.14869],"iteration":659,"passed_time":2.060812578,"remaining_time":1.061630722},
{"learn":[86587.31723],"iteration":660,"passed_time":2.06384451,"remaining_time":1.058461859},
{"learn":[86564.01554],"iteration":661,"passed_time":2.066740783,"remaining_time":1.055224146},
{"learn":[86546.64676],"iteration":662,"passed_time":2.069729589,"remaining_time":1.052034497},
{"learn":[86524.44352],"iteration":663,"passed_time":2.072798329,"remaining_time":1.048885901},
{"learn":[86498.92709],"iteration":664,"passed_time":2.07648329,"remaining_time":1.046047973},
{"learn":[86485.97344],"iteration":665,"passed_time":2.079780063,"remaining_time":1.043012824},
{"learn":[86464.20791],"iteration":666,"passed_time":2.08269282,"remaining_time":1.039785171},
{"learn":[86442.64398],"iteration":667,"passed_time":2.085501728,"remaining_time":1.036506847},
{"learn":[86423.85868],"iteration":668,"passed_time":2.088163492,"remaining_time":1.033157124},
{"learn":[86398.95525],"iteration":669,"passed_time":2.091024101,"remaining_time":1.029907393},
{"learn":[86380.7879],"iteration":670,"passed_time":2.094014268,"remaining_time":1.026722346},
{"learn":[86350.93314],"iteration":671,"passed_time":2.096783973,"remaining_time":1.023430272},
{"learn":[86330.83933],"iteration":672,"passed_time":2.099542714,"remaining_time":1.020134424},
{"learn":[86319.00296],"iteration":673,"passed_time":2.102179494,"remaining_time":1.01678118},
{"learn":[86299.01344],"iteration":674,"passed_time":2.104875338,"remaining_time":1.013458496},
{"learn":[86272.072],"iteration":675,"passed_time":2.107688524,"remaining_time":1.010193908},
{"learn":[86254.34714],"iteration":676,"passed_time":2.110674033,"remaining_time":1.00701287},
{"learn":[86231.73686],"iteration":677,"passed_time":2.113755933,"remaining_time":1.003878187},
{"learn":[86215.71668],"iteration":678,"passed_time":2.117246338,"remaining_time":1.000936781},
{"learn":[86200.16431],"iteration":679,"passed_time":2.120121513,"remaining_time":0.9977042414},
{"learn":[86193.24357],"iteration":680,"passed_time":2.123073438,"remaining_time":0.994508703},
{"learn":[86180.2342],"iteration":681,"passed_time":2.126394861,"remaining_time":0.9914861669},
{"learn":[86166.55385],"iteration":682,"passed_time":2.129267137,"remaining_time":0.9882542934},
{"learn":[86144.96561],"iteration":683,"passed_time":2.132356949,"remaining_time":0.9851239705},
{"learn":[86131.97324],"iteration":684,"passed_time":2.135081814,"remaining_time":0.9818259437},
{"learn":[86124.14249],"iteration":685,"passed_time":2.138621449,"remaining_time":0.9789025292},
{"learn":[86109.09512],"iteration":686,"passed_time":2.141672245,"remaining_time":0.9757546035},
{"learn":[86085.89314],"iteration":687,"passed_time":2.144391566,"remaining_time":0.9724566405},
{"learn":[86064.70287],"iteration":688,"passed_time":2.147297471,"remaining_time":0.9692445768},
{"learn":[86044.14843],"iteration":689,"passed_time":2.150046198,"remaining_time":0.9659627844},
{"learn":[86026.01713],"iteration":690,"passed_time":2.153172152,"remaining_time":0.962851223},
{"learn":[86012.96785],"iteration":691,"passed_time":2.155913031,"remaining_time":0.9595682275},
{"learn":[85997.79719],"iteration":692,"passed_time":2.159082851,"remaining_time":0.9564768187},
{"learn":[85988.51858],"iteration":693,"passed_time":2.161725033,"remaining_time":0.953152536},
{"learn":[85969.56772],"iteration":694,"passed_time":2.164626492,"remaining_time":0.949944},
{"learn":[85949.09636],"iteration":695,"passed_time":2.167658719,"remaining_time":0.9467934636},
{"learn":[85940.35599],"iteration":696,"passed_time":2.170417884,"remaining_time":0.9435245606},
{"learn":[85925.95901],"iteration":697,"passed_time":2.173555407,"remaining_time":0.9404208206},
{"learn":[85911.87107],"iteration":698,"passed_time":2.176583857,"remaining_time":0.9372700158},
{"learn":[85898.86827],"iteration":699,"passed_time":2.17946023,"remaining_time":0.9340543844},
{"learn":[85885.31143],"iteration":700,"passed_time":2.182503138,"remaining_time":0.9309107535},
{"learn":[85865.73707],"iteration":701,"passed_time":2.185300318,"remaining_time":0.9276630981},
{"learn":[85847.95427],"iteration":702,"passed_time":2.188041831,"remaining_time":0.9243932061},
{"learn":[85821.74638],"iteration":703,"passed_time":2.191132649,"remaining_time":0.9212716819},
{"learn":[85800.19689],"iteration":704,"passed_time":2.194098988,"remaining_time":0.9180981583},
{"learn":[85788.03375],"iteration":705,"passed_time":2.197317765,"remaining_time":0.9150303439},
{"learn":[85769.45723],"iteration":706,"passed_time":2.200088049,"remaining_time":0.9117762352},
{"learn":[85760.0318],"iteration":707,"passed_time":2.202673064,"remaining_time":0.9084470831},
{"learn":[85737.01892],"iteration":708,"passed_time":2.205526147,"remaining_time":0.9052300545},
{"learn":[85723.32852],"iteration":709,"passed_time":2.208255546,"remaining_time":0.9019635327},
{"learn":[85710.39243],"iteration":710,"passed_time":2.211561064,"remaining_time":0.8989326968},
{"learn":[85688.77227],"iteration":711,"passed_time":2.214382233,"remaining_time":0.8957051729},
{"learn":[85677.9532],"iteration":712,"passed_time":2.217077006,"remaining_time":0.8924279114},
{"learn":[85668.96492],"iteration":713,"passed_time":2.219825765,"remaining_time":0.889173906},
{"learn":[85652.66969],"iteration":714,"passed_time":2.222884176,"remaining_time":0.8860447417},
{"learn":[85635.21276],"iteration":715,"passed_time":2.225724341,"remaining_time":0.8828292079},
{"learn":[85629.33565],"iteration":716,"passed_time":2.22892098,"remaining_time":0.8797554216},
{"learn":[85615.91372],"iteration":717,"passed_time":2.231483576,"remaining_time":0.8764322681},
{"learn":[85601.22821],"iteration":718,"passed_time":2.234234483,"remaining_time":0.8731848258},
{"learn":[85583.46103],"iteration":719,"passed_time":2.236960349,"remaining_time":0.8699290247},
{"learn":[85567.36673],"iteration":720,"passed_time":2.239804521,"remaining_time":0.8667204735},
{"learn":[85550.29216],"iteration":721,"passed_time":2.24333274,"remaining_time":0.8637763183},
{"learn":[85525.21702],"iteration":722,"passed_time":2.246171995,"remaining_time":0.8605665873},
{"learn":[85505.81318],"iteration":723,"passed_time":2.24897936,"remaining_time":0.857345723},
{"learn":[85481.85839],"iteration":724,"passed_time":2.251668898,"remaining_time":0.854081306},
{"learn":[85466.82098],"iteration":725,"passed_time":2.254489867,"remaining_time":0.8508680765},
{"learn":[85447.44594],"iteration":726,"passed_time":2.257858938,"remaining_time":0.847861747},
{"learn":[85425.61213],"iteration":727,"passed_time":2.261904828,"remaining_time":0.8451072982},
{"learn":[85412.80585],"iteration":728,"passed_time":2.264811253,"remaining_time":0.8419257195},
{"learn":[85397.3029],"iteration":729,"passed_time":2.267637785,"remaining_time":0.8387153451},
{"learn":[85377.13245],"iteration":730,"passed_time":2.270756042,"remaining_time":0.8356133725},
{"learn":[85350.94892],"iteration":731,"passed_time":2.274025396,"remaining_time":0.8325666752},
{"learn":[85337.22982],"iteration":732,"passed_time":2.277692235,"remaining_time":0.8296641566},
{"learn":[85314.88457],"iteration":733,"passed_time":2.280646616,"remaining_time":0.8265013623},
{"learn":[85296.84988],"iteration":734,"passed_time":2.283427734,"remaining_time":0.823276666},
{"learn":[85275.17415],"iteration":735,"passed_time":2.286296151,"remaining_time":0.8200844888},
{"learn":[85254.56368],"iteration":736,"passed_time":2.289500156,"remaining_time":0.8170129459},
{"learn":[85239.80001],"iteration":737,"passed_time":2.292422046,"remaining_time":0.8138408889},
{"learn":[85228.42329],"iteration":738,"passed_time":2.295234675,"remaining_time":0.8106309204},
{"learn":[85217.78101],"iteration":739,"passed_time":2.297895096,"remaining_time":0.8073685473},
{"learn":[85201.01487],"iteration":740,"passed_time":2.300621494,"remaining_time":0.8041308594},
{"learn":[85190.06941],"iteration":741,"passed_time":2.303735216,"remaining_time":0.8010292261},
{"learn":[85172.2885],"iteration":742,"passed_time":2.306967902,"remaining_time":0.7979687091},
{"learn":[85152.55168],"iteration":743,"passed_time":2.309832343,"remaining_time":0.7947810214},
{"learn":[85140.86916],"iteration":744,"passed_time":2.31264328,"remaining_time":0.7915758879},
{"learn":[85125.45862],"iteration":745,"passed_time":2.315494439,"remaining_time":0.7883855062},
{"learn":[85107.88641],"iteration":746,"passed_time":2.318479395,"remaining_time":0.785241348},
{"learn":[85080.00401],"iteration":747,"passed_time":2.322286262,"remaining_time":0.782374516},
{"learn":[85061.92256],"iteration":748,"passed_time":2.32552839,"remaining_time":0.7793159225},
{"learn":[85041.27321],"iteration":749,"passed_time":2.32840672,"remaining_time":0.7761355734},
{"learn":[85020.54519],"iteration":750,"passed_time":2.331466738,"remaining_time":0.7730162686},
{"learn":[84995.38876],"iteration":751,"passed_time":2.334648228,"remaining_time":0.7699371815},
{"learn":[84978.61437],"iteration":752,"passed_time":2.337576186,"remaining_time":0.7667746587},
{"learn":[84971.61475],"iteration":753,"passed_time":2.340399865,"remaining_time":0.7635787357},
{"learn":[84961.37848],"iteration":754,"passed_time":2.343087974,"remaining_time":0.7603398061},
{"learn":[84946.28977],"iteration":755,"passed_time":2.345682052,"remaining_time":0.7570719852},
{"learn":[84933.46079],"iteration":756,"passed_time":2.348359968,"remaining_time":0.7538328562},
{"learn":[84932.9195],"iteration":757,"passed_time":2.351426339,"remaining_time":0.7507192271},
{"learn":[84921.60943],"iteration":758,"passed_time":2.354332788,"remaining_time":0.7475549433},
{"learn":[84903.7526],"iteration":759,"passed_time":2.357451574,"remaining_time":0.7444583918},
{"learn":[84889.92715],"iteration":760,"passed_time":2.360368194,"remaining_time":0.7412982895},
{"learn":[84873.68632],"iteration":761,"passed_time":2.363272256,"remaining_time":0.738134904},
{"learn":[84860.97298],"iteration":762,"passed_time":2.366294975,"remaining_time":0.7350090551},
{"learn":[84851.55055],"iteration":763,"passed_time":2.369248281,"remaining_time":0.7318620346},
{"learn":[84830.63805],"iteration":764,"passed_time":2.372205815,"remaining_time":0.7287168189},
{"learn":[84827.40536],"iteration":765,"passed_time":2.374905424,"remaining_time":0.7254933018},
{"learn":[84809.87684],"iteration":766,"passed_time":2.377733828,"remaining_time":0.7223102762},
{"learn":[84795.97851],"iteration":767,"passed_time":2.380436462,"remaining_time":0.7190901812},
{"learn":[84778.73018],"iteration":768,"passed_time":2.383665575,"remaining_time":0.716029581},
{"learn":[84753.24253],"iteration":769,"passed_time":2.386530332,"remaining_time":0.7128597096},
{"learn":[84737.65171],"iteration":770,"passed_time":2.38966254,"remaining_time":0.709770067},
{"learn":[84715.8647],"iteration":771,"passed_time":2.392543545,"remaining_time":0.7066061246},
{"learn":[84693.24667],"iteration":772,"passed_time":2.395321896,"remaining_time":0.703412769},
{"learn":[84666.30185],"iteration":773,"passed_time":2.416086889,"remaining_time":0.7054723992},
{"learn":[84652.25482],"iteration":774,"passed_time":2.420007278,"remaining_time":0.702582758},
{"learn":[84642.19298],"iteration":775,"passed_time":2.424154309,"remaining_time":0.699755883},
{"learn":[84628.68567],"iteration":776,"passed_time":2.428229584,"remaining_time":0.6969050157},
{"learn":[84624.67012],"iteration":777,"passed_time":2.432003723,"remaining_time":0.6939650726},
{"learn":[84605.6425],"iteration":778,"passed_time":2.435970721,"remaining_time":0.6910777012},
{"learn":[84595.53061],"iteration":779,"passed_time":2.440006322,"remaining_time":0.6882069112},
{"learn":[84571.36379],"iteration":780,"passed_time":2.443895757,"remaining_time":0.6852921522},
{"learn":[84568.38188],"iteration":781,"passed_time":2.446668387,"remaining_time":0.6820635656},
{"learn":[84558.33219],"iteration":782,"passed_time":2.449753176,"remaining_time":0.6789226555},
{"learn":[84537.96376],"iteration":783,"passed_time":2.45273969,"remaining_time":0.6757548125},
{"learn":[84529.6185],"iteration":784,"passed_time":2.455617212,"remaining_time":0.6725575805},
{"learn":[84501.30751],"iteration":785,"passed_time":2.458644434,"remaining_time":0.6694019197},
{"learn":[84495.61039],"iteration":786,"passed_time":2.461132862,"remaining_time":0.6661007618},
{"learn":[84485.19196],"iteration":787,"passed_time":2.463781557,"remaining_time":0.6628447844},
{"learn":[84470.21869],"iteration":788,"passed_time":2.466954978,"remaining_time":0.6597306723},
{"learn":[84449.13826],"iteration":789,"passed_time":2.469922689,"remaining_time":0.6565617275},
{"learn":[84434.08181],"iteration":790,"passed_time":2.472824008,"remaining_time":0.6533757492},
{"learn":[84415.37823],"iteration":791,"passed_time":2.476110854,"remaining_time":0.6502917395},
{"learn":[84397.802],"iteration":792,"passed_time":2.479006917,"remaining_time":0.6471052104},
{"learn":[84384.37793],"iteration":793,"passed_time":2.482196448,"remaining_time":0.6439955519},
{"learn":[84383.93944],"iteration":794,"passed_time":2.484761374,"remaining_time":0.6407246311},
{"learn":[84372.40907],"iteration":795,"passed_time":2.487503469,"remaining_time":0.6375008891},
{"learn":[84352.52327],"iteration":796,"passed_time":2.490686968,"remaining_time":0.6343907837},
{"learn":[84333.87022],"iteration":797,"passed_time":2.493455569,"remaining_time":0.6311754699},
{"learn":[84317.02465],"iteration":798,"passed_time":2.496404299,"remaining_time":0.6280065883},
{"learn":[84307.90762],"iteration":799,"passed_time":2.499470061,"remaining_time":0.6248675151},
{"learn":[84290.02625],"iteration":800,"passed_time":2.502568516,"remaining_time":0.6217367475},
{"learn":[84280.85938],"iteration":801,"passed_time":2.505731255,"remaining_time":0.6186219307},
{"learn":[84275.99634],"iteration":802,"passed_time":2.508438157,"remaining_time":0.6153951644},
{"learn":[84248.31874],"iteration":803,"passed_time":2.511193959,"remaining_time":0.6121816118},
{"learn":[84237.98903],"iteration":804,"passed_time":2.514304898,"remaining_time":0.6090552238},
{"learn":[84226.5392],"iteration":805,"passed_time":2.517154883,"remaining_time":0.6058660637},
{"learn":[84194.99511],"iteration":806,"passed_time":2.520502077,"remaining_time":0.6027966554},
{"learn":[84181.69272],"iteration":807,"passed_time":2.523269374,"remaining_time":0.5995887621},
{"learn":[84150.73458],"iteration":808,"passed_time":2.526054784,"remaining_time":0.5963862346},
{"learn":[84138.52364],"iteration":809,"passed_time":2.528766636,"remaining_time":0.5931674826},
{"learn":[84132.19456],"iteration":810,"passed_time":2.531592707,"remaining_time":0.5899765989},
{"learn":[84113.58196],"iteration":811,"passed_time":2.534833171,"remaining_time":0.5868825568},
{"learn":[84093.76704],"iteration":812,"passed_time":2.5376716,"remaining_time":0.5836956816},
{"learn":[84084.66064],"iteration":813,"passed_time":2.540319325,"remaining_time":0.5804660865},
{"learn":[84073.29861],"iteration":814,"passed_time":2.543069224,"remaining_time":0.5772611121},
{"learn":[84062.55568],"iteration":815,"passed_time":2.546173634,"remaining_time":0.574137192},
{"learn":[84040.98321],"iteration":816,"passed_time":2.548971659,"remaining_time":0.5709446923},
{"learn":[84038.00234],"iteration":817,"passed_time":2.553003878,"remaining_time":0.5680277577},
{"learn":[84026.3981],"iteration":818,"passed_time":2.555683847,"remaining_time":0.5648092507},
{"learn":[84022.54813],"iteration":819,"passed_time":2.558277616,"remaining_time":0.5615731353},
{"learn":[84017.35605],"iteration":820,"passed_time":2.561184168,"remaining_time":0.5584067797},
{"learn":[84003.79399],"iteration":821,"passed_time":2.564044844,"remaining_time":0.5552311219},
{"learn":[83971.72416],"iteration":822,"passed_time":2.567112515,"remaining_time":0.5521007475},
{"learn":[83954.51609],"iteration":823,"passed_time":2.569765474,"remaining_time":0.5488819458},
{"learn":[83942.10039],"iteration":824,"passed_time":2.572482045,"remaining_time":0.5456780095},
{"learn":[83931.64184],"iteration":825,"passed_time":2.575136106,"remaining_time":0.5424620852},
{"learn":[83917.15835],"iteration":826,"passed_time":2.578067589,"remaining_time":0.5393055537},
{"learn":[83893.51706],"iteration":827,"passed_time":2.581074767,"remaining_time":0.5361652897},
{"learn":[83881.3202],"iteration":828,"passed_time":2.583997193,"remaining_time":0.5330078649},
{"learn":[83857.24177],"iteration":829,"passed_time":2.586716869,"remaining_time":0.5298094792},
{"learn":[83841.49437],"iteration":830,"passed_time":2.589483955,"remaining_time":0.5266218874},
{"learn":[83824.69134],"iteration":831,"passed_time":2.592296031,"remaining_time":0.5234443908},
{"learn":[83813.75221],"iteration":832,"passed_time":2.595187616,"remaining_time":0.5202837117},
{"learn":[83813.54322],"iteration":833,"passed_time":2.597430627,"remaining_time":0.5169945852},
{"learn":[83795.78151],"iteration":834,"passed_time":2.600535389,"remaining_time":0.5138782504},
{"learn":[83777.07331],"iteration":835,"passed_time":2.604595745,"remaining_time":0.5109494045},
{"learn":[83763.04705],"iteration":836,"passed_time":2.607300525,"remaining_time":0.5077538657},
{"learn":[83742.22661],"iteration":837,"passed_time":2.610233991,"remaining_time":0.504603707},
{"learn":[83728.0486],"iteration":838,"passed_time":2.613319276,"remaining_time":0.5014831985},
{"learn":[83718.89784],"iteration":839,"passed_time":2.616215021,"remaining_time":0.4983266707},
{"learn":[83701.53658],"iteration":840,"passed_time":2.6189353,"remaining_time":0.4951375894},
{"learn":[83693.41555],"iteration":841,"passed_time":2.62149544,"remaining_time":0.4919195719},
{"learn":[83688.86572],"iteration":842,"passed_time":2.62413715,"remaining_time":0.4887183067},
{"learn":[83674.45717],"iteration":843,"passed_time":2.627468439,"remaining_time":0.4856458252},
{"learn":[83656.46227],"iteration":844,"passed_time":2.630488197,"remaining_time":0.4825155865},
{"learn":[83645.36683],"iteration":845,"passed_time":2.633317008,"remaining_time":0.4793508501},
{"learn":[83644.99032],"iteration":846,"passed_time":2.635990922,"remaining_time":0.4761589268},
{"learn":[83625.1356],"iteration":847,"passed_time":2.638693278,"remaining_time":0.4729733234},
{"learn":[83609.80461],"iteration":848,"passed_time":2.641615952,"remaining_time":0.4698280433},
{"learn":[83591.69239],"iteration":849,"passed_time":2.64501336,"remaining_time":0.4667670636},
{"learn":[83583.20942],"iteration":850,"passed_time":2.648125699,"remaining_time":0.4636553809},
{"learn":[83562.85638],"iteration":851,"passed_time":2.650980377,"remaining_time":0.4604989386},
{"learn":[83550.7473],"iteration":852,"passed_time":2.653629857,"remaining_time":0.4573078417},
{"learn":[83538.40834],"iteration":853,"passed_time":2.656224866,"remaining_time":0.4541087007},
{"learn":[83522.5651],"iteration":854,"passed_time":2.659806252,"remaining_time":0.4510782533},
{"learn":[83508.63594],"iteration":855,"passed_time":2.66269914,"remaining_time":0.4479306965},
{"learn":[83487.64508],"iteration":856,"passed_time":2.665512975,"remaining_time":0.4447705431},
{"learn":[83463.29146],"iteration":857,"passed_time":2.668167794,"remaining_time":0.4415848796},
{"learn":[83449.05841],"iteration":858,"passed_time":2.670847261,"remaining_time":0.4384044979},
{"learn":[83432.91162],"iteration":859,"passed_time":2.673612623,"remaining_time":0.4352392641},
{"learn":[83418.57481],"iteration":860,"passed_time":2.676751275,"remaining_time":0.4321352233},
{"learn":[83397.86543],"iteration":861,"passed_time":2.679499668,"remaining_time":0.4289686244},
{"learn":[83386.19763],"iteration":862,"passed_time":2.682177046,"remaining_time":0.4257917211},
{"learn":[83371.32735],"iteration":863,"passed_time":2.684924714,"remaining_time":0.4226270382},
{"learn":[83354.01685],"iteration":864,"passed_time":2.687642329,"remaining_time":0.4194586294},
{"learn":[83334.83866],"iteration":865,"passed_time":2.691709732,"remaining_time":0.4165001202},
{"learn":[83324.89914],"iteration":866,"passed_time":2.694846252,"remaining_time":0.4133962531},
{"learn":[83320.79753],"iteration":867,"passed_time":2.698120596,"remaining_time":0.4103132704},
{"learn":[83312.31466],"iteration":868,"passed_time":2.700755907,"remaining_time":0.4071335142},
{"learn":[83292.28163],"iteration":869,"passed_time":2.703422475,"remaining_time":0.4039596802},
{"learn":[83270.5424],"iteration":870,"passed_time":2.706686028,"remaining_time":0.4008754277},
{"learn":[83250.66737],"iteration":871,"passed_time":2.709703011,"remaining_time":0.3977545704},
{"learn":[83237.2606],"iteration":872,"passed_time":2.712952344,"remaining_time":0.3946677522},
{"learn":[83220.34497],"iteration":873,"passed_time":2.715710252,"remaining_time":0.391509716},
{"learn":[83208.62111],"iteration":874,"passed_time":2.718374544,"remaining_time":0.3883392206},
{"learn":[83190.68139],"iteration":875,"passed_time":2.721325448,"remaining_time":0.3852104515},
{"learn":[83185.68351],"iteration":876,"passed_time":2.724157654,"remaining_time":0.3820654407},
{"learn":[83175.82645],"iteration":877,"passed_time":2.726867693,"remaining_time":0.3789041669},
{"learn":[83161.82807],"iteration":878,"passed_time":2.729750349,"remaining_time":0.3757676818},
{"learn":[83144.25226],"iteration":879,"passed_time":2.732457758,"remaining_time":0.372607876},
{"learn":[83119.31119],"iteration":880,"passed_time":2.735565431,"remaining_time":0.3695031627},
{"learn":[83110.01915],"iteration":881,"passed_time":2.738473179,"remaining_time":0.3663716951},
{"learn":[83086.27067],"iteration":882,"passed_time":2.741562138,"remaining_time":0.3632647454},
{"learn":[83075.41925],"iteration":883,"passed_time":2.744662211,"remaining_time":0.3601592947},
{"learn":[83062.36879],"iteration":884,"passed_time":2.747419399,"remaining_time":0.3570093004},
{"learn":[83051.50741],"iteration":885,"passed_time":2.750004407,"remaining_time":0.3538380388},
{"learn":[83039.40114],"iteration":886,"passed_time":2.752928643,"remaining_time":0.3507113153},
{"learn":[83032.43373],"iteration":887,"passed_time":2.755984127,"remaining_time":0.3476016016},
{"learn":[83022.07333],"iteration":888,"passed_time":2.758894342,"remaining_time":0.3444738717},
{"learn":[83006.94675],"iteration":889,"passed_time":2.76219671,"remaining_time":0.341395099},
{"learn":[82999.16585],"iteration":890,"passed_time":2.764937768,"remaining_time":0.3382471569},
{"learn":[82979.92139],"iteration":891,"passed_time":2.767717119,"remaining_time":0.3351047632},
{"learn":[82965.41769],"iteration":892,"passed_time":2.77045542,"remaining_time":0.3319582642},
{"learn":[82954.37339],"iteration":893,"passed_time":2.77336984,"remaining_time":0.3288335605},
{"learn":[82929.75564],"iteration":894,"passed_time":2.776432801,"remaining_time":0.3257267532},
{"learn":[82917.90465],"iteration":895,"passed_time":2.779113281,"remaining_time":0.3225756487},
{"learn":[82909.9355],"iteration":896,"passed_time":2.782035004,"remaining_time":0.3194532948},
{"learn":[82905.89626],"iteration":897,"passed_time":2.784839672,"remaining_time":0.316318092},
{"learn":[82892.25109],"iteration":898,"passed_time":2.788052778,"remaining_time":0.3132295112},
{"learn":[82877.52003],"iteration":899,"passed_time":2.791314564,"remaining_time":0.3101460627},
{"learn":[82864.67515],"iteration":900,"passed_time":2.794195873,"remaining_time":0.3070204122},
{"learn":[82843.67027],"iteration":901,"passed_time":2.797174412,"remaining_time":0.3039058674},
{"learn":[82833.65804],"iteration":902,"passed_time":2.799869522,"remaining_time":0.3007611779},
{"learn":[82818.41363],"iteration":903,"passed_time":2.802596485,"remaining_time":0.2976208656},
{"learn":[82803.6854],"iteration":904,"passed_time":2.805879179,"remaining_time":0.2945398033},
{"learn":[82787.34286],"iteration":905,"passed_time":2.809041962,"remaining_time":0.2914458547},
{"learn":[82774.15358],"iteration":906,"passed_time":2.811850251,"remaining_time":0.2883154061},
{"learn":[82765.35063],"iteration":907,"passed_time":2.814520199,"remaining_time":0.2851716501},
{"learn":[82748.11356],"iteration":908,"passed_time":2.817217927,"remaining_time":0.2820317176},
{"learn":[82733.57543],"iteration":909,"passed_time":2.820255644,"remaining_time":0.2789263824},
{"learn":[82725.86637],"iteration":910,"passed_time":2.822890108,"remaining_time":0.2757817998},
{"learn":[82717.10146],"iteration":911,"passed_time":2.825905851,"remaining_time":0.272675126},
{"learn":[82706.90092],"iteration":912,"passed_time":2.829035538,"remaining_time":0.2695795091},
{"learn":[82701.59268],"iteration":913,"passed_time":2.831838184,"remaining_time":0.2664530458},
{"learn":[82689.62193],"iteration":914,"passed_time":2.834721145,"remaining_time":0.2633347512},
{"learn":[82683.07881],"iteration":915,"passed_time":2.837927122,"remaining_time":0.260246592},
{"learn":[82667.89752],"iteration":916,"passed_time":2.84094836,"remaining_time":0.2571414546},
{"learn":[82651.61318],"iteration":917,"passed_time":2.844319899,"remaining_time":0.2540677905},
{"learn":[82640.97459],"iteration":918,"passed_time":2.846968177,"remaining_time":0.2509297305},
{"learn":[82623.47409],"iteration":919,"passed_time":2.849698662,"remaining_time":0.2477998836},
{"learn":[82617.31584],"iteration":920,"passed_time":2.852683023,"remaining_time":0.2446926806},
{"learn":[82602.52138],"iteration":921,"passed_time":2.855416196,"remaining_time":0.2415644938},
{"learn":[82594.68105],"iteration":922,"passed_time":2.858610811,"remaining_time":0.2384756581},
{"learn":[82583.23068],"iteration":923,"passed_time":2.86129515,"remaining_time":0.2353446227},
{"learn":[82573.07439],"iteration":924,"passed_time":2.863983712,"remaining_time":0.2322148956},
{"learn":[82561.84578],"iteration":925,"passed_time":2.866677194,"remaining_time":0.2290865144},
{"learn":[82558.03294],"iteration":926,"passed_time":2.869535083,"remaining_time":0.2259720184},
{"learn":[82534.54678],"iteration":927,"passed_time":2.872595558,"remaining_time":0.2228737933},
{"learn":[82521.09756],"iteration":928,"passed_time":2.875554571,"remaining_time":0.2197678951},
{"learn":[82507.29082],"iteration":929,"passed_time":2.878439284,"remaining_time":0.2166567203},
{"learn":[82488.30094],"iteration":930,"passed_time":2.88145718,"remaining_time":0.2135559027},
{"learn":[82471.46704],"iteration":931,"passed_time":2.884448086,"remaining_time":0.2104532938},
{"learn":[82450.82539],"iteration":932,"passed_time":2.887556048,"remaining_time":0.2073593304},
{"learn":[82435.07151],"iteration":933,"passed_time":2.890491873,"remaining_time":0.204253173},
{"learn":[82419.31185],"iteration":934,"passed_time":2.893239435,"remaining_time":0.2011342922},
{"learn":[82407.66743],"iteration":935,"passed_time":2.895965036,"remaining_time":0.1980147033},
{"learn":[82393.37933],"iteration":936,"passed_time":2.898670621,"remaining_time":0.1948946096},
{"learn":[82375.85143],"iteration":937,"passed_time":2.901705847,"remaining_time":0.1917971882},
{"learn":[82364.39658],"iteration":938,"passed_time":2.90474981,"remaining_time":0.1887004669},
{"learn":[82351.27138],"iteration":939,"passed_time":2.907799362,"remaining_time":0.1856042146},
{"learn":[82332.32089],"iteration":940,"passed_time":2.910643859,"remaining_time":0.1824952048},
{"learn":[82313.38236],"iteration":941,"passed_time":2.913404807,"remaining_time":0.1793816123},
{"learn":[82307.32563],"iteration":942,"passed_time":2.916300891,"remaining_time":0.1762769362},
{"learn":[82293.28343],"iteration":943,"passed_time":2.920192866,"remaining_time":0.1732317802},
{"learn":[82271.45895],"iteration":944,"passed_time":2.924373257,"remaining_time":0.1702016181},
{"learn":[82258.93386],"iteration":945,"passed_time":2.92873031,"remaining_time":0.1671791086},
{"learn":[82250.76992],"iteration":946,"passed_time":2.933264028,"remaining_time":0.1641636679},
{"learn":[82234.12306],"iteration":947,"passed_time":2.93746133,"remaining_time":0.1611265708},
{"learn":[82233.73341],"iteration":948,"passed_time":2.940452403,"remaining_time":0.158022205},
{"learn":[82218.3166],"iteration":949,"passed_time":2.94342482,"remaining_time":0.1549170958},
{"learn":[82210.50251],"iteration":950,"passed_time":2.946477951,"remaining_time":0.1518164244},
{"learn":[82201.52157],"iteration":951,"passed_time":2.949699656,"remaining_time":0.1487243524},
{"learn":[82183.50594],"iteration":952,"passed_time":2.95311439,"remaining_time":0.1456415282},
{"learn":[82163.29266],"iteration":953,"passed_time":2.95649801,"remaining_time":0.1425565078},
{"learn":[82146.86819],"iteration":954,"passed_time":2.959672741,"remaining_time":0.1394610192},
{"learn":[82134.91968],"iteration":955,"passed_time":2.962936259,"remaining_time":0.1363694512},
{"learn":[82115.88062],"iteration":956,"passed_time":2.966477146,"remaining_time":0.1332899867},
{"learn":[82108.04708],"iteration":957,"passed_time":2.969755396,"remaining_time":0.1301980445},
{"learn":[82100.1605],"iteration":958,"passed_time":2.972684422,"remaining_time":0.1270907834},
{"learn":[82089.70668],"iteration":959,"passed_time":2.976088189,"remaining_time":0.1240036746},
{"learn":[82074.1381],"iteration":960,"passed_time":2.979393228,"remaining_time":0.1209119},
{"learn":[82064.79908],"iteration":961,"passed_time":2.983158036,"remaining_time":0.1178378434},
{"learn":[82038.06131],"iteration":962,"passed_time":2.986576622,"remaining_time":0.1147490498},
{"learn":[82020.77056],"iteration":963,"passed_time":2.98963968,"remaining_time":0.1116462951},
{"learn":[82000.40249],"iteration":964,"passed_time":2.993433114,"remaining_time":0.1085701129},
{"learn":[81982.65448],"iteration":965,"passed_time":2.996391339,"remaining_time":0.1054630492},
{"learn":[81962.87755],"iteration":966,"passed_time":2.999745108,"remaining_time":0.1023697917},
{"learn":[81952.78004],"iteration":967,"passed_time":3.002939965,"remaining_time":0.09927074264},
{"learn":[81935.49884],"iteration":968,"passed_time":3.005928249,"remaining_time":0.09616488721},
{"learn":[81913.73913],"iteration":969,"passed_time":3.008930428,"remaining_time":0.09305970394},
{"learn":[81901.52914],"iteration":970,"passed_time":3.012028798,"remaining_time":0.08995760571},
{"learn":[81889.16869],"iteration":971,"passed_time":3.015576852,"remaining_time":0.08686846899},
{"learn":[81877.01842],"iteration":972,"passed_time":3.019223747,"remaining_time":0.08378113172},
{"learn":[81857.29605],"iteration":973,"passed_time":3.022529886,"remaining_time":0.08068354932},
{"learn":[81843.97181],"iteration":974,"passed_time":3.025418535,"remaining_time":0.07757483423},
{"learn":[81827.65751],"iteration":975,"passed_time":3.028455456,"remaining_time":0.07447021614},
{"learn":[81804.64107],"iteration":976,"passed_time":3.031934465,"remaining_time":0.07137614401},
{"learn":[81792.16377],"iteration":977,"passed_time":3.035537305,"remaining_time":0.06828407026},
{"learn":[81775.88945],"iteration":978,"passed_time":3.038492131,"remaining_time":0.06517705286},
{"learn":[81759.79429],"iteration":979,"passed_time":3.041712503,"remaining_time":0.06207576536},
{"learn":[81751.25889],"iteration":980,"passed_time":3.044771894,"remaining_time":0.0589711172},
{"learn":[81730.6598],"iteration":981,"passed_time":3.047821902,"remaining_time":0.05586638925},
{"learn":[81722.37759],"iteration":982,"passed_time":3.051260385,"remaining_time":0.05276849089},
{"learn":[81712.91103],"iteration":983,"passed_time":3.054293644,"remaining_time":0.04966331128},
{"learn":[81702.79784],"iteration":984,"passed_time":3.057085125,"remaining_time":0.04655459581},
{"learn":[81684.72475],"iteration":985,"passed_time":3.060094443,"remaining_time":0.04344961684},
{"learn":[81670.9656],"iteration":986,"passed_time":3.063154992,"remaining_time":0.04034550647},
{"learn":[81661.21465],"iteration":987,"passed_time":3.066270146,"remaining_time":0.03724214752},
{"learn":[81648.91339],"iteration":988,"passed_time":3.06902792,"remaining_time":0.03413478981},
{"learn":[81637.18169],"iteration":989,"passed_time":3.071736527,"remaining_time":0.03102764169},
{"learn":[81627.96742],"iteration":990,"passed_time":3.074331697,"remaining_time":0.02792026768},
{"learn":[81616.90097],"iteration":991,"passed_time":3.077347594,"remaining_time":0.02481731931},
{"learn":[81603.9487],"iteration":992,"passed_time":3.080372332,"remaining_time":0.02171460859},
{"learn":[81595.9518],"iteration":993,"passed_time":3.083717085,"remaining_time":0.01861398643},
{"learn":[81582.91363],"iteration":994,"passed_time":3.087081282,"remaining_time":0.01551297127},
{"learn":[81566.42779],"iteration":995,"passed_time":3.090191016,"remaining_time":0.01241040569},
{"learn":[81545.89728],"iteration":996,"passed_time":3.093061557,"remaining_time":0.009307105989},
{"learn":[81529.54702],"iteration":997,"passed_time":3.096592364,"remaining_time":0.00620559592},
{"learn":[81515.78965],"iteration":998,"passed_time":3.099969188,"remaining_time":0.00310307226},
{"learn":[81504.92467],"iteration":999,"passed_time":3.103008748,"remaining_time":0}
]}